[
  {
    "text": "\n\t\t\n\t\t\t\n\t\t\t\n\t\t\n\t",
    "url": "https://www.minnpost.com/"
  },
  {
    "text": "Donate",
    "url": "https://www.minnpost.com/support"
  },
  {
    "text": "Home",
    "url": "https://www.minnpost.com"
  },
  {
    "text": "News",
    "url": "https://www.minnpost.com/news"
  },
  {
    "text": "Arts & Culture",
    "url": "https://www.minnpost.com/arts-culture"
  },
  {
    "text": "Health",
    "url": "https://www.minnpost.com/health"
  },
  {
    "text": "Opinion",
    "url": "https://www.minnpost.com/opinion"
  },
  {
    "text": "Events",
    "url": "https://www.minnpost.com/events"
  },
  {
    "text": "AboutAbout Us",
    "url": "https://www.minnpost.com/about"
  },
  {
    "text": "Newsletters",
    "url": "https://www.minnpost.com/newsletters"
  },
  {
    "text": "Your Account",
    "url": "https://www.minnpost.com/user"
  },
  {
    "text": "Log In",
    "url": "https://www.minnpost.com/user/login"
  },
  {
    "text": "Create Account",
    "url": "https://www.minnpost.com/user/register"
  },
  {
    "text": "Change Your Password",
    "url": "https://www.minnpost.com/user/password"
  },
  {
    "text": "Search",
    "url": "/?s="
  },
  {
    "text": "",
    "url": "#"
  },
  {
    "text": "Topics",
    "url": "/topics/"
  },
  {
    "text": "2022 Election",
    "url": "https://www.minnpost.com/tag/2022-election"
  },
  {
    "text": "COVID-19",
    "url": "https://www.minnpost.com/tag/covid-19"
  },
  {
    "text": "Metro",
    "url": "https://www.minnpost.com/metro"
  },
  {
    "text": "State Government",
    "url": "https://www.minnpost.com/state-government"
  },
  {
    "text": "Greater Minnesota",
    "url": "https://www.minnpost.com/greater-minnesota"
  },
  {
    "text": "National",
    "url": "https://www.minnpost.com/national"
  },
  {
    "text": "Education",
    "url": "https://www.minnpost.com/education"
  },
  {
    "text": "Environment",
    "url": "https://www.minnpost.com/environment"
  },
  {
    "text": "Mental Health & Addiction",
    "url": "https://www.minnpost.com/mental-health-addiction"
  },
  {
    "text": "Economy",
    "url": "https://www.minnpost.com/economy"
  },
  {
    "text": "News",
    "url": "https://www.minnpost.com/news/"
  },
  {
    "text": "Metro",
    "url": "https://www.minnpost.com/metro/"
  },
  {
    "text": "How state and federal consent decrees could make way for broader scope of changes to Minneapolis policing",
    "url": "https://www.minnpost.com/metro/2022/07/how-state-and-federal-consent-decrees-could-make-way-for-broader-scope-of-changes-to-minneapolis-policing/"
  },
  {
    "text": "Mohamed Ibrahim",
    "url": "https://www.minnpost.com/author/mohamed-ibrahim/"
  },
  {
    "text": "\n\t\t\t\t\t\t\t",
    "url": "https://www.minnpost.com/metro/2022/07/how-state-and-federal-consent-decrees-could-make-way-for-broader-scope-of-changes-to-minneapolis-policing/"
  },
  {
    "text": "The Glean: Latest headlines from around Minnesota",
    "url": "https://www.minnpost.com/glean/"
  },
  {
    "text": "Friday\u2019s Mega Millions jackpot worth nearly $1.3 billion",
    "url": "https://www.minnpost.com/glean/2022/07/fridays-mega-millions-jackpot-worth-nearly-1-3-billion/"
  },
  {
    "text": "News",
    "url": "https://www.minnpost.com/news/"
  },
  {
    "text": "Elections",
    "url": "https://www.minnpost.com/elections/"
  },
  {
    "text": "Chalking tires, video surveillance in dispute over residency in GOP-held Senate district",
    "url": "https://www.minnpost.com/elections/2022/07/chalking-tires-video-surveillance-in-dispute-over-residency-in-gop-held-senate-district/"
  },
  {
    "text": "Walker Orenstein",
    "url": "https://www.minnpost.com/author/walker-orenstein/"
  },
  {
    "text": "\n\t\t\t\t\t\t\t",
    "url": "https://www.minnpost.com/elections/2022/07/chalking-tires-video-surveillance-in-dispute-over-residency-in-gop-held-senate-district/"
  },
  {
    "text": "News",
    "url": "https://www.minnpost.com/news/"
  },
  {
    "text": "Metro",
    "url": "https://www.minnpost.com/metro/"
  },
  {
    "text": "\u2018We have a voice\u2019: Minneapolis pact with Native community gets another refresh",
    "url": "https://www.minnpost.com/metro/2022/07/we-have-a-voice-minneapolis-pact-with-native-community-gets-another-refresh/"
  },
  {
    "text": "Solomon Gustavo",
    "url": "https://www.minnpost.com/author/solomon-gustavo/"
  },
  {
    "text": "\n\t\t\t\t\t\t\t",
    "url": "https://www.minnpost.com/metro/2022/07/we-have-a-voice-minneapolis-pact-with-native-community-gets-another-refresh/"
  },
  {
    "text": "News",
    "url": "https://www.minnpost.com/news/"
  },
  {
    "text": "Elections",
    "url": "https://www.minnpost.com/elections/"
  },
  {
    "text": "Most, but not all, 1st District voters will vote twice on Aug. 9 to decide who will represent them in Congress",
    "url": "https://www.minnpost.com/elections/2022/07/most-but-not-all-1st-district-voters-will-vote-twice-on-aug-9-to-decide-who-will-represent-them-in-congress/"
  },
  {
    "text": "Ana Radelat",
    "url": "https://www.minnpost.com/author/ana-radelat/"
  },
  {
    "text": "\n\t\t\t\t\t\t\t",
    "url": "https://www.minnpost.com/elections/2022/07/most-but-not-all-1st-district-voters-will-vote-twice-on-aug-9-to-decide-who-will-represent-them-in-congress/"
  },
  {
    "text": "News",
    "url": "https://www.minnpost.com/news/"
  },
  {
    "text": "Elections",
    "url": "https://www.minnpost.com/elections/"
  },
  {
    "text": "Phillips: Democrats need \u2018new generation\u2019 of leadership, not Biden in 2024",
    "url": "https://www.minnpost.com/elections/2022/07/phillips-democrats-need-new-generation-of-leadership-not-biden-in-2024/"
  },
  {
    "text": "Ana Radelat",
    "url": "https://www.minnpost.com/author/ana-radelat/"
  },
  {
    "text": "\n\t\t\t\t\t\t\t",
    "url": "https://www.minnpost.com/elections/2022/07/phillips-democrats-need-new-generation-of-leadership-not-biden-in-2024/"
  },
  {
    "text": "News",
    "url": "https://www.minnpost.com/news/"
  },
  {
    "text": "D.C. Memo",
    "url": "https://www.minnpost.com/dc-memo/"
  },
  {
    "text": "D.C. Memo: Surprise deal on key Democratic legislation, Justice Department turns up heat on Trump and Phillips says no to Biden in 2024",
    "url": "https://www.minnpost.com/dc-memo/2022/07/d-c-memo-surprise-deal-on-key-democratic-legislation-justice-department-turns-up-heat-on-trump-and-phillips-says-no-to-biden-in-2024/"
  },
  {
    "text": "Ana Radelat",
    "url": "https://www.minnpost.com/author/ana-radelat/"
  },
  {
    "text": "\n\t\t\t\t\t\t\t",
    "url": "https://www.minnpost.com/dc-memo/2022/07/d-c-memo-surprise-deal-on-key-democratic-legislation-justice-department-turns-up-heat-on-trump-and-phillips-says-no-to-biden-in-2024/"
  },
  {
    "text": "Arts & Culture",
    "url": "https://www.minnpost.com/arts-culture/"
  },
  {
    "text": "Artscape",
    "url": "https://www.minnpost.com/artscape/"
  },
  {
    "text": "Weekend picks: It\u2019s hip-hop x 2 with Herb Johnson III at the Southern and BRKFST Dance + the Minnesota Orchestra",
    "url": "https://www.minnpost.com/artscape/2022/07/weekend-picks-its-hip-hop-x-2-with-herb-johnson-iii-at-the-southern-and-brkfst-dance-the-minnesota-orchestra/"
  },
  {
    "text": "Sheila Regan",
    "url": "https://www.minnpost.com/author/sheila-regan/"
  },
  {
    "text": "\n\t\t\t\t\t\t\t",
    "url": "https://www.minnpost.com/artscape/2022/07/weekend-picks-its-hip-hop-x-2-with-herb-johnson-iii-at-the-southern-and-brkfst-dance-the-minnesota-orchestra/"
  },
  {
    "text": "News",
    "url": "https://www.minnpost.com/news/"
  },
  {
    "text": "Elections",
    "url": "https://www.minnpost.com/elections/"
  },
  {
    "text": "2022 Campaign Finance Dashboard",
    "url": "https://www.minnpost.com/elections/2022/07/2022-campaign-finance-dashboard/"
  },
  {
    "text": "Tom Nehil",
    "url": "https://www.minnpost.com/author/tom-nehil/"
  },
  {
    "text": "Greta Kaul",
    "url": "https://www.minnpost.com/author/greta-kaul/"
  },
  {
    "text": "\n\t\t\t\t\t\t\t",
    "url": "https://www.minnpost.com/elections/2022/07/2022-campaign-finance-dashboard/"
  },
  {
    "text": "News",
    "url": "https://www.minnpost.com/news/"
  },
  {
    "text": "State Government",
    "url": "https://www.minnpost.com/state-government/"
  },
  {
    "text": "Capitol watchers \u2018befuddled\u2019 by rare bonding bill stall under legislative dealmaker Tom Bakk",
    "url": "https://www.minnpost.com/state-government/2022/07/capitol-watchers-befuddled-by-rare-bonding-bill-stall-under-legislative-dealmaker-bakk/"
  },
  {
    "text": "Walker Orenstein",
    "url": "https://www.minnpost.com/author/walker-orenstein/"
  },
  {
    "text": "\n\t\t\t\t\t\t\t",
    "url": "https://www.minnpost.com/state-government/2022/07/capitol-watchers-befuddled-by-rare-bonding-bill-stall-under-legislative-dealmaker-bakk/"
  },
  {
    "text": "\n\t\t\t\t\t\t\t",
    "url": "https://www.minnpost.com/news/2022/06/abortion-pills-likely-to-gain-popularity-in-minnesota-and-elsewhere-expected-to-be-next-legal-battleground/"
  },
  {
    "text": "Abortion pills, likely to gain popularity in Minnesota and elsewhere, expected to be next legal battleground",
    "url": "https://www.minnpost.com/news/2022/06/abortion-pills-likely-to-gain-popularity-in-minnesota-and-elsewhere-expected-to-be-next-legal-battleground/"
  },
  {
    "text": "\n\t\t\t\t\t\t\t",
    "url": "https://www.minnpost.com/data/2022/05/what-we-know-about-abortions-in-minnesota/"
  },
  {
    "text": "What we know about abortions in Minnesota",
    "url": "https://www.minnpost.com/data/2022/05/what-we-know-about-abortions-in-minnesota/"
  },
  {
    "text": "\n\t\t\t\t\t\t\t",
    "url": "https://www.minnpost.com/macro-micro-minnesota/2022/06/is-the-fed-risking-a-recession/"
  },
  {
    "text": "Is the Fed risking a recession?",
    "url": "https://www.minnpost.com/macro-micro-minnesota/2022/06/is-the-fed-risking-a-recession/"
  },
  {
    "text": "\n\t\t\t\t\t\t\t",
    "url": "https://www.minnpost.com/state-government/2022/06/poll-walz-holds-slight-edge-over-republican-scott-jensen-among-minnesota-voters/"
  },
  {
    "text": "Poll: Walz holds slight edge over Republican Scott Jensen among Minnesota voters",
    "url": "https://www.minnpost.com/state-government/2022/06/poll-walz-holds-slight-edge-over-republican-scott-jensen-among-minnesota-voters/"
  },
  {
    "text": "\n\t\t\t\t\t\t\t",
    "url": "https://www.minnpost.com/data/2022/06/minnpost-poll-reveals-two-thirds-of-minnesotans-oppose-ban-on-abortions/"
  },
  {
    "text": "MinnPost poll reveals two-thirds of Minnesotans oppose ban on abortions",
    "url": "https://www.minnpost.com/data/2022/06/minnpost-poll-reveals-two-thirds-of-minnesotans-oppose-ban-on-abortions/"
  },
  {
    "text": "other free newsletter options",
    "url": "/newsletters"
  },
  {
    "text": "News",
    "url": "https://www.minnpost.com/news/"
  },
  {
    "text": "State Government",
    "url": "https://www.minnpost.com/state-government/"
  },
  {
    "text": "How the Minnesota GOP\u2019s endorsement process pushes Republican candidates further to the right",
    "url": "https://www.minnpost.com/state-government/2022/05/how-the-minnesota-gops-endorsement-process-pushes-republican-candidates-further-to-the-right/"
  },
  {
    "text": "Peter Callaghan",
    "url": "https://www.minnpost.com/author/peter-callaghan/"
  },
  {
    "text": "News",
    "url": "https://www.minnpost.com/news/"
  },
  {
    "text": "Elections",
    "url": "https://www.minnpost.com/elections/"
  },
  {
    "text": "Who\u2019s running in Minnesota in 2022: Statewide offices and U.S. House",
    "url": "https://www.minnpost.com/elections/2022/06/whos-running-in-minnesota-in-2022/"
  },
  {
    "text": "Peter Callaghan",
    "url": "https://www.minnpost.com/author/peter-callaghan/"
  },
  {
    "text": "Ashley Hackett",
    "url": "https://www.minnpost.com/author/ashley-hackett/"
  },
  {
    "text": "Walker Orenstein",
    "url": "https://www.minnpost.com/author/walker-orenstein/"
  },
  {
    "text": "Tom Nehil",
    "url": "https://www.minnpost.com/author/tom-nehil/"
  },
  {
    "text": "News",
    "url": "https://www.minnpost.com/news/"
  },
  {
    "text": "Elections",
    "url": "https://www.minnpost.com/elections/"
  },
  {
    "text": "Who\u2019s running for the Minnesota Legislature in 2022",
    "url": "https://www.minnpost.com/elections/2022/04/whos-running-for-the-minnesota-legislature-in-2022/"
  },
  {
    "text": "Walker Orenstein",
    "url": "https://www.minnpost.com/author/walker-orenstein/"
  },
  {
    "text": "Peter Callaghan",
    "url": "https://www.minnpost.com/author/peter-callaghan/"
  },
  {
    "text": "\n\t\t\t\t\t\t\t",
    "url": "https://www.minnpost.com/eric-black-ink/2022/07/klobuchar-and-walz-for-president-new-washington-post-lists-them-as-possible-candidates/"
  },
  {
    "text": "Opinion",
    "url": "https://www.minnpost.com/opinion/"
  },
  {
    "text": "Eric Black Ink",
    "url": "https://www.minnpost.com/eric-black-ink/"
  },
  {
    "text": "Klobuchar and Walz for president? New Washington Post list has them as possible candidates",
    "url": "https://www.minnpost.com/eric-black-ink/2022/07/klobuchar-and-walz-for-president-new-washington-post-lists-them-as-possible-candidates/"
  },
  {
    "text": "Eric Black",
    "url": "https://www.minnpost.com/author/eric-black/"
  },
  {
    "text": "\n\t\t\t\t\t\t\t",
    "url": "https://www.minnpost.com/community-voices/2022/07/after-two-decades-of-studying-voucher-programs-im-now-firmly-opposed-to-them/"
  },
  {
    "text": "Opinion",
    "url": "https://www.minnpost.com/opinion/"
  },
  {
    "text": "Community Voices",
    "url": "https://www.minnpost.com/community-voices/"
  },
  {
    "text": "After two decades of studying voucher programs, I\u2019m now firmly opposed to them",
    "url": "https://www.minnpost.com/community-voices/2022/07/after-two-decades-of-studying-voucher-programs-im-now-firmly-opposed-to-them/"
  },
  {
    "text": "\n\t\t\t\t\t\t\t",
    "url": "https://www.minnpost.com/eric-black-ink/2022/07/poll-shows-some-shift-in-views-of-former-president-trump-since-hearings-on-jan-6/"
  },
  {
    "text": "Opinion",
    "url": "https://www.minnpost.com/opinion/"
  },
  {
    "text": "Eric Black Ink",
    "url": "https://www.minnpost.com/eric-black-ink/"
  },
  {
    "text": "Poll shows some shift in views of former President Trump since hearings on Jan. 6",
    "url": "https://www.minnpost.com/eric-black-ink/2022/07/poll-shows-some-shift-in-views-of-former-president-trump-since-hearings-on-jan-6/"
  },
  {
    "text": "Eric Black",
    "url": "https://www.minnpost.com/author/eric-black/"
  },
  {
    "text": "\n\t\t\t\t\t\t\t",
    "url": "https://www.minnpost.com/community-voices/2022/07/sure-the-twin-cities-rank-among-the-nations-best-park-systems-but-not-for-all/"
  },
  {
    "text": "Opinion",
    "url": "https://www.minnpost.com/opinion/"
  },
  {
    "text": "Community Voices",
    "url": "https://www.minnpost.com/community-voices/"
  },
  {
    "text": "Sure the Twin Cities rank among the nation\u2019s best park systems, but not for all",
    "url": "https://www.minnpost.com/community-voices/2022/07/sure-the-twin-cities-rank-among-the-nations-best-park-systems-but-not-for-all/"
  },
  {
    "text": "\n\t\t\t\t\t\t\t",
    "url": "https://www.minnpost.com/eric-black-ink/2022/07/yale-historian-snyder-ukraine-most-likely-will-win-the-war/"
  },
  {
    "text": "Opinion",
    "url": "https://www.minnpost.com/opinion/"
  },
  {
    "text": "Eric Black Ink",
    "url": "https://www.minnpost.com/eric-black-ink/"
  },
  {
    "text": "Yale historian Snyder: Ukraine most likely will win the war",
    "url": "https://www.minnpost.com/eric-black-ink/2022/07/yale-historian-snyder-ukraine-most-likely-will-win-the-war/"
  },
  {
    "text": "Eric Black",
    "url": "https://www.minnpost.com/author/eric-black/"
  },
  {
    "text": "\n\t\t\t\t\t\t\t",
    "url": "https://www.minnpost.com/community-voices/2022/07/does-u-s-have-two-systems-of-justice-we-await-an-answer-in-attorney-generals-jan-6-decision/"
  },
  {
    "text": "Opinion",
    "url": "https://www.minnpost.com/opinion/"
  },
  {
    "text": "Community Voices",
    "url": "https://www.minnpost.com/community-voices/"
  },
  {
    "text": "Does U.S. have two systems of justice? We await an answer in attorney general\u2019s Jan. 6 decision",
    "url": "https://www.minnpost.com/community-voices/2022/07/does-u-s-have-two-systems-of-justice-we-await-an-answer-in-attorney-generals-jan-6-decision/"
  },
  {
    "text": "Why Biden shouldn't run again \u2014 and should tell us that now",
    "url": "https://www.minnpost.com/eric-black-ink/2022/07/why-biden-shouldnt-run-again-and-should-tell-us-that-now/"
  },
  {
    "text": "Omar, Samuels locked in intra-party Democratic conflict",
    "url": "https://www.minnpost.com/elections/2022/07/omar-samuels-locked-in-intra-party-democratic-conflict/"
  },
  {
    "text": "Yale historian Snyder: Ukraine most likely will win the war",
    "url": "https://www.minnpost.com/eric-black-ink/2022/07/yale-historian-snyder-ukraine-most-likely-will-win-the-war/"
  },
  {
    "text": "Phillips: Democrats need 'new generation' of leadership, not Biden in 2024",
    "url": "https://www.minnpost.com/elections/2022/07/phillips-democrats-need-new-generation-of-leadership-not-biden-in-2024/"
  },
  {
    "text": "After two decades of studying voucher programs, I\u2019m now firmly opposed to them",
    "url": "https://www.minnpost.com/community-voices/2022/07/after-two-decades-of-studying-voucher-programs-im-now-firmly-opposed-to-them/"
  },
  {
    "text": "Environment",
    "url": "https://www.minnpost.com/environment/"
  },
  {
    "text": "Projects to expand the power grid will make room for more renewable energy and less coal",
    "url": "https://www.minnpost.com/environment/2022/07/projects-to-expand-the-power-grid-will-make-room-for-more-renewable-energy-and-less-coal/"
  },
  {
    "text": "Mohamed Ibrahim",
    "url": "https://www.minnpost.com/author/mohamed-ibrahim/"
  },
  {
    "text": "Tens of thousands lobbied for and against mining moratorium in Superior National Forest",
    "url": "https://www.minnpost.com/environment/2022/07/tens-of-thousands-lobbied-for-and-against-mining-moratorium-in-superior-national-forest/"
  },
  {
    "text": "Ana Radelat",
    "url": "https://www.minnpost.com/author/ana-radelat/"
  },
  {
    "text": "What a Supreme Court EPA ruling means for Minnesota and the fight against climate change",
    "url": "https://www.minnpost.com/environment/2022/07/what-a-supreme-court-epa-ruling-means-for-minnesota-and-the-fight-against-climate-change/"
  },
  {
    "text": "Mohamed Ibrahim",
    "url": "https://www.minnpost.com/author/mohamed-ibrahim/"
  },
  {
    "text": "The Northern Metals shredder is gone, but environmental dangers remain\u00a0",
    "url": "https://www.minnpost.com/race-health-equity/2022/07/the-northern-metals-shredder-is-gone-but-environmental-dangers-remain/"
  },
  {
    "text": "Ava Kian",
    "url": "https://www.minnpost.com/author/ava-kian/"
  },
  {
    "text": "Energy deal with bipartisan support is a no go with Minnesota Legislature unable to pass a budget",
    "url": "https://www.minnpost.com/greater-minnesota/2022/06/energy-deal-with-bipartisan-support-is-a-no-go-with-minnesota-legislature-unable-to-pass-a-budget/"
  },
  {
    "text": "Walker Orenstein",
    "url": "https://www.minnpost.com/author/walker-orenstein/"
  },
  {
    "text": "Education",
    "url": "https://www.minnpost.com/education/"
  },
  {
    "text": "So, does the overturning of Roe help Democrats or Republicans come November?",
    "url": "https://www.minnpost.com/politics-policy/2022/06/so-does-the-overturning-of-roe-help-democrats-or-republicans-come-november/"
  },
  {
    "text": "Peter Callaghan",
    "url": "https://www.minnpost.com/author/peter-callaghan/"
  },
  {
    "text": "Surprise gift sets Minneapolis North High seniors on the path to success",
    "url": "https://www.minnpost.com/education/2022/05/surprise-gift-sets-minneapolis-north-high-seniors-on-the-path-to-success/"
  },
  {
    "text": "Harry Colbert",
    "url": "https://www.minnpost.com/author/harry-colbert/"
  },
  {
    "text": "Counseling positions to be cut at Minneapolis\u2019 Southwest High; student ratio could jump by 100 students",
    "url": "https://www.minnpost.com/race-health-equity/2022/05/counseling-positions-to-be-cut-at-minneapolis-southwest-high-student-ratio-could-jump-by-100-students/"
  },
  {
    "text": "Ava Kian",
    "url": "https://www.minnpost.com/author/ava-kian/"
  },
  {
    "text": "Minneapolis Public Schools adds violence interrupters to provide after-school safety",
    "url": "https://www.minnpost.com/metro/2022/05/minneapolis-public-schools-adds-violence-interrupters-to-provide-after-school-safety/"
  },
  {
    "text": "Solomon Gustavo",
    "url": "https://www.minnpost.com/author/solomon-gustavo/"
  },
  {
    "text": "How do strikers envision improving the mental health of Minneapolis students?",
    "url": "https://www.minnpost.com/race-health-equity/2022/03/how-do-strikers-envision-improving-the-mental-health-of-minneapolis-students/"
  },
  {
    "text": "Ava Kian",
    "url": "https://www.minnpost.com/author/ava-kian/"
  },
  {
    "text": "Arts & Culture",
    "url": "https://www.minnpost.com/arts-culture/"
  },
  {
    "text": "\u2018This is the best job ever\u2019: Circus Juventas traces 600 years of circus history with \u2018Confetti!\u2019 \u2014 and marks 28 years as a youth performing arts school",
    "url": "https://www.minnpost.com/artscape/2022/07/this-is-the-best-job-ever-circus-juventas-traces-600-years-of-circus-history-with-confetti-and-marks-28-years-as-a-youth-performing-arts-school/"
  },
  {
    "text": "Sheila Regan",
    "url": "https://www.minnpost.com/author/sheila-regan/"
  },
  {
    "text": "The Minneapolis Aquatennial has been drawing crowds every July since 1940",
    "url": "https://www.minnpost.com/mnopedia/2022/07/the-minneapolis-aquatennial-has-been-drawing-crowds-every-july-since-1940/"
  },
  {
    "text": "Samuel Meshbesher",
    "url": "https://www.minnpost.com/author/samuel-meshbesher/"
  },
  {
    "text": "Weekend picks: Lots of magic to discover, including \u2018History of Religion\u2019 at the Illusion and Maggie Thompson\u2019s \u2018Just Friends\u2019 at Bockley",
    "url": "https://www.minnpost.com/artscape/2022/07/weekend-picks-lots-of-magic-to-discover-including-history-of-religion-at-the-illusion-and-maggie-thompsons-just-friends-at-bockley/"
  },
  {
    "text": "Sheila Regan",
    "url": "https://www.minnpost.com/author/sheila-regan/"
  },
  {
    "text": "Cafesjian Art Trust, with Chihuly glass, Moran seascapes and more, is coming soon to Shoreview",
    "url": "https://www.minnpost.com/artscape/2022/07/cafesjian-art-trust-with-chihuly-glass-moran-seascapes-and-more-is-coming-soon-to-shoreview/"
  },
  {
    "text": "Sheila Regan",
    "url": "https://www.minnpost.com/author/sheila-regan/"
  },
  {
    "text": "The expansion of American Crystal Sugar into the Red River Valley",
    "url": "https://www.minnpost.com/mnopedia/2022/07/the-expansion-of-american-crystal-sugar-into-the-red-river-valley/"
  },
  {
    "text": "Inside MinnPost",
    "url": "https://www.minnpost.com/inside-minnpost/"
  },
  {
    "text": "Keeping MinnPost news paywall free",
    "url": "https://www.minnpost.com/inside-minnpost/2022/06/keeping-minnpost-news-paywall-free/"
  },
  {
    "text": "Tanner Curl",
    "url": "https://www.minnpost.com/author/tanner-curl/"
  },
  {
    "text": "The MinnPost newsroom is small but mighty",
    "url": "https://www.minnpost.com/inside-minnpost/2022/06/the-minnpost-newsroom-is-small-but-mighty/"
  },
  {
    "text": "Laura Lindsay",
    "url": "https://www.minnpost.com/author/laura-lindsay/"
  },
  {
    "text": "The history of the griot",
    "url": "https://www.minnpost.com/inside-minnpost/2022/06/the-history-of-the-griot/"
  },
  {
    "text": "Harry Colbert",
    "url": "https://www.minnpost.com/author/harry-colbert/"
  },
  {
    "text": "MinnPost announces new hire in Mohamed Ibrahim",
    "url": "https://www.minnpost.com/inside-minnpost/2022/06/minnpost-announces-new-hire-in-mohamed-ibrahim/"
  },
  {
    "text": "Harry Colbert",
    "url": "https://www.minnpost.com/author/harry-colbert/"
  },
  {
    "text": "At MinnPost, we\u2019re turning our eyes to November",
    "url": "https://www.minnpost.com/inside-minnpost/2022/06/at-minnpost-were-turning-our-eyes-to-november/"
  },
  {
    "text": "Walker Orenstein",
    "url": "https://www.minnpost.com/author/walker-orenstein/"
  },
  {
    "text": "",
    "url": "https://www.minneapolisfoundation.org"
  },
  {
    "text": "",
    "url": "https://www.bluecrossmn.com/"
  },
  {
    "text": "",
    "url": "https://greatriverenergy.com/"
  },
  {
    "text": "",
    "url": "http://www.ucare.org"
  },
  {
    "text": "",
    "url": "https://ottobremer.org/"
  },
  {
    "text": "top philanthropic supporters",
    "url": "/major-supporters/"
  },
  {
    "text": "\n\t\t\n\t\t\t\n\t\t\t\n\t\t\n\t",
    "url": "https://www.minnpost.com/"
  },
  {
    "text": "About Us",
    "url": "https://www.minnpost.com/about"
  },
  {
    "text": "Careers",
    "url": "https://www.minnpost.com/careers"
  },
  {
    "text": "Advertise",
    "url": "https://www.minnpost.com/advertise"
  },
  {
    "text": "Membership",
    "url": "https://www.minnpost.com/support"
  },
  {
    "text": "Help",
    "url": "https://www.minnpost.com/help"
  },
  {
    "text": "Contact",
    "url": "https://www.minnpost.com/contact-us"
  },
  {
    "text": "Submit a Tip",
    "url": "https://www.minnpost.com/submit-a-tip"
  },
  {
    "text": "Code of Ethics",
    "url": "https://www.minnpost.com/minnpost-code-of-ethics"
  },
  {
    "text": "Terms of Use",
    "url": "https://www.minnpost.com/terms-of-use"
  },
  {
    "text": "Privacy Policy",
    "url": "https://www.minnpost.com/privacy"
  },
  {
    "text": "Twitter",
    "url": "https://twitter.com/MinnPost"
  },
  {
    "text": "Facebook",
    "url": "https://www.facebook.com/MinnPost"
  },
  {
    "text": "Instagram",
    "url": "https://www.instagram.com/MinnPost"
  },
  {
    "text": "RSS Feeds List",
    "url": "https://www.minnpost.com/rss-feed-list"
  },
  {
    "text": "612.455.6950",
    "url": "tel:612.455.6950"
  },
  {
    "text": "",
    "url": "https://wpvip.com/?utm_source=vip_powered_wpcom&utm_medium=web&utm_campaign=VIP%20Footer%20Credit&utm_term=www.minnpost.com"
  },
  {
    "text": "\n\t\tClose window\n\t\t\n\t",
    "url": "#"
  },
  {
    "text": "Attribution-NonCommercial-NoDerivatives Creative Commons license",
    "url": "https://creativecommons.org/licenses/by-nc-nd/4.0/"
  },
  {
    "text": "republishing guidelines",
    "url": "/republication-policy/"
  },
  {
    "text": "editors@minnpost.com",
    "url": "mailto:editors@minnpost.com"
  }
]
