[
  {
    "text": "\nRecibe noticias ",
    "url": "javascript:void(0)"
  },
  {
    "text": "\n\n\n\n\n\n\n\n\n",
    "url": "https://www.animalpolitico.com"
  },
  {
    "text": "\nRecibe noticias ",
    "url": "javascript:void(0)"
  },
  {
    "text": "\n\nSuscr\u00edbete\n",
    "url": "https://suscribete.editorialanimal.mx?origin=ap"
  },
  {
    "text": "\n\nVerificaciones, noticias y visualizaciones del COVID-19\n\n\n",
    "url": "https://www.animalpolitico.com/noticias-coronavirus-covid-2019-verificacion/"
  },
  {
    "text": "\n\nInicia sesi\u00f3n\n\n",
    "url": "https://www.animalpolitico.com/acceder/"
  },
  {
    "text": "\n\nEn portada \n",
    "url": "https://www.animalpolitico.com"
  },
  {
    "text": "\n\nM\u00e9xico Desigual \n",
    "url": "https://www.animalpolitico.com/mexico-desigual/"
  },
  {
    "text": "\n\nEl Plumaje \n",
    "url": "https://www.animalpolitico.com/plumaje/"
  },
  {
    "text": "\n\nEl Sabueso \n",
    "url": "https://www.animalpolitico.com/sabueso/"
  },
  {
    "text": "\n\nEspeciales \n",
    "url": "https://www.animalpolitico.com/especiales/"
  },
  {
    "text": "\n\nVideo \n",
    "url": "https://www.animalpolitico.com/videos/"
  },
  {
    "text": "\n\nHablemos de... \n",
    "url": "https://www.animalpolitico.com/hablemos-de/"
  },
  {
    "text": "\n\nArchivo \n",
    "url": "https://www.animalpolitico.com/archivo/"
  },
  {
    "text": "\n\n",
    "url": "https://www.facebook.com/pajaropolitico"
  },
  {
    "text": "\n\n",
    "url": "https://twitter.com/pajaropolitico"
  },
  {
    "text": "\n\n",
    "url": "https://www.youtube.com/user/pajaropolitico2012"
  },
  {
    "text": "\n\n",
    "url": "https://www.instagram.com/pajaropolitico/"
  },
  {
    "text": "\n\n",
    "url": "https://flipboard.com/@AnimalPolitico"
  },
  {
    "text": "\nRecibe noticias ",
    "url": "javascript:void(0)"
  },
  {
    "text": "\n\n\n",
    "url": "https://www.animalpolitico.com"
  },
  {
    "text": "\n\n",
    "url": "https://www.facebook.com/pajaropolitico"
  },
  {
    "text": "\n\n",
    "url": "https://twitter.com/pajaropolitico"
  },
  {
    "text": "\n\n",
    "url": "https://www.youtube.com/user/pajaropolitico2012"
  },
  {
    "text": "\n\n",
    "url": "https://www.instagram.com/pajaropolitico/"
  },
  {
    "text": "\n\n",
    "url": "https://flipboard.com/@AnimalPolitico"
  },
  {
    "text": "\n\nSuscr\u00edbete\n",
    "url": "https://www.animalpolitico.com/suscribete/?v3"
  },
  {
    "text": "\n\nM\u00e9xico Desigual \n",
    "url": "https://www.animalpolitico.com/mexico-desigual/"
  },
  {
    "text": "\n\nEl Plumaje \n",
    "url": "https://www.animalpolitico.com/plumaje/"
  },
  {
    "text": "\n\nEl Sabueso \n",
    "url": "https://www.animalpolitico.com/sabueso/"
  },
  {
    "text": "\n\nEspeciales \n",
    "url": "https://www.animalpolitico.com/especiales/"
  },
  {
    "text": "\n\nVideo \n",
    "url": "https://www.animalpolitico.com/videos/"
  },
  {
    "text": "\n\nHablemos de... \n",
    "url": "https://www.animalpolitico.com/hablemos-de/"
  },
  {
    "text": "\n\nArchivo \n",
    "url": "https://www.animalpolitico.com/archivo/"
  },
  {
    "text": "\n\nInicia sesi\u00f3n\n\n",
    "url": "https://www.animalpolitico.com/acceder/"
  },
  {
    "text": "\n\nVerificaciones, noticias y visualizaciones del COVID-19\n\n\n",
    "url": "https://www.animalpolitico.com/noticias-coronavirus-covid-2019-verificacion/"
  },
  {
    "text": "\nSuscr\u00edbete al canal de Youtube\n",
    "url": "https://www.youtube.com/user/pajaropolitico2012?sub_confirmation=1"
  },
  {
    "text": "\n\n",
    "url": "https://twitter.com/intent/tweet?url=%7Burl%7D&via=pajaropolitico&text=%7Btitle%7D"
  },
  {
    "text": "\n\n",
    "url": "https://www.facebook.com/sharer/sharer.php?u=%7Burl%7D"
  },
  {
    "text": "\n\n",
    "url": "https://api.whatsapp.com/send?text=%7Btitle%7D+%7Burl%7D"
  },
  {
    "text": "\n\n",
    "url": "mailto:?subject=%7Btitle%7D&body=%7Burl%7D"
  },
  {
    "text": "\n\n",
    "url": "https://www.animalpolitico.com"
  },
  {
    "text": "\n\n\n",
    "url": "https://www.animalpolitico.com/2022/07/cecilia-monzon-arrestan-autor-material-feminicidio/"
  },
  {
    "text": "\n\n\nArrestan al presunto autor material del feminicidio de Cecilia Monz\u00f3n \n\n",
    "url": "https://www.animalpolitico.com/2022/07/cecilia-monzon-arrestan-autor-material-feminicidio/"
  },
  {
    "text": "\n\n\n\n\n\n\n>Matan en Puebla a la activista y abogada feminista Cecilia Monz\u00f3n \n\n21 de mayo, 2022 \n\n",
    "url": "https://www.animalpolitico.com/2022/05/matan-abogada-activista-cecilia-monzon/"
  },
  {
    "text": "\n\n\n\n\n\n\n>Expareja de Cecilia Monz\u00f3n orden\u00f3 su asesinato; se negaba a pagar pensi\u00f3n \n\n7 de junio, 2022 \n\n",
    "url": "https://www.animalpolitico.com/2022/06/detienen-a-tres-presuntos-responsables-asesinato-abogada-cecilia-monzon/"
  },
  {
    "text": "\n\n\n\n\n\n\nElecci\u00f3n Morena: denuncian acarreo, compra de voto y quema de urnas \n\n",
    "url": "https://www.animalpolitico.com/2022/07/eleccion-morena-denuncian-acarreo-compra-voto-quema-urnas/"
  },
  {
    "text": "\n\n\n\n\n\n\nDetienen al exdirector jur\u00eddico de la BJ por presunto enriquecimiento il\u00edcito \n\n",
    "url": "https://www.animalpolitico.com/2022/07/detienen-exdirector-juridico-benito-juarez-enriquecimiento-ilicito/"
  },
  {
    "text": "\n\n\n\n\n\n\n",
    "url": "https://suscribete.editorialanimal.mx?origin=ap"
  },
  {
    "text": "\n\n \n\n\n\n\nM\u00e9xico registra 19 mil 352 contagio de COVID y 109 muertes m\u00e1s en un d\u00eda \n\n\n",
    "url": "https://www.animalpolitico.com/2022/07/covid-mexico-19-mil-contagios-muertes-salud/"
  },
  {
    "text": "\n\n \n\n\n\n\nEl Sabueso \n\nSe eleva gasto en el Tren Maya; persiste subejercicio en Salud y Educaci\u00f3n \n\n\n",
    "url": "https://www.animalpolitico.com/elsabueso/gasto-tren-maya-subejercicio-salud-educacion/"
  },
  {
    "text": "\n\n \n\n\n\n\n Tras protesta, empiezan a viajar a Finlandia jugadoras de futbol americano \n\n\n",
    "url": "https://www.animalpolitico.com/2022/07/jugadoras-seleccion-futbol-americano-mundial-finlandia-protestas/"
  },
  {
    "text": "\n\n \n\n\n\n\nElecci\u00f3n Morena. Si hay acarreo y pruebas, se anular\u00e1 distrito: Delgado \n\n\n",
    "url": "https://www.animalpolitico.com/2022/07/eleccion-morena-acarreo-anulara-votacion-delgado/"
  },
  {
    "text": "\n\n \n\n\n\n\nEn M\u00e9xico, nadie cuida a quienes cuidan \n\n\n",
    "url": "https://www.animalpolitico.com/2022/07/nadie-cuida-mexico-a-quienes-cuidan/"
  },
  {
    "text": "\n\n \n\n\n\n\nBiden da positivo a COVID por segunda ocasi\u00f3n; retomar\u00e1 estricto confinamiento \n\n\n",
    "url": "https://www.animalpolitico.com/2022/07/biden-covid-positivo-presidente-eu-confinamiento/"
  },
  {
    "text": "\n\n \n\n\n\n\nBBC News Mundo \n\nViruela del mono: qu\u00e9 se sabe de las primeras muertes en AL y Europa. \n\n\n",
    "url": "https://www.animalpolitico.com/bbc/viruela-mono-primeras-muertes-america-latina-europa/"
  },
  {
    "text": "\n\n\n\n\n\n\nAnimalMX:\nMastectom\u00eda no es igual a mutilaci\u00f3n: perspectiva de g\u00e9nero en sector salud \n\n",
    "url": "https://animal.mx/salud-y-estilo-de-vida/mastectomia-no-mutilacion-perspectiva-de-genero-sector-salud/"
  },
  {
    "text": "\n\n\n\n\n\n\nAnimal Gourmet:\n\u00bfC\u00f3mo preparar la nogada perfecta? 2 recetas que no tienen desperdicio \n\n",
    "url": "https://www.animalgourmet.com/2022/07/19/preparar-nogada-2-opciones/"
  },
  {
    "text": "\n\n\n\n\n\n\nNewsweek M\u00e9xico:\nLos ni\u00f1os sin nombre: ciudadanos invisibles para el gobierno mexicano \n\n",
    "url": "https://newsweekespanol.com/2022/07/ninos-identidad-ciudadanos-invisibles-gobierno-mexicano/"
  },
  {
    "text": "\n\n\n\n\n\n\nEl Sabueso:\nEstos tanques no repliegan protestas en China, es un ejercicio militar \n\n",
    "url": "https://www.animalpolitico.com/elsabueso/tanques-no-repliegan-protestas-china-es-ejercicio-militar/"
  },
  {
    "text": "\n\n\n\n\n\n\n:\nSostenibilidad y responsabilidad social: tres pasos para hacerlos realidad \n\n",
    "url": "https://www.animalpolitico.com/2022/07/sostenibilidad-y-responsabilidad-social-tres-pasos-para-hacerlos-realidad/"
  },
  {
    "text": "\n\n",
    "url": "https://www.animalpolitico.com/plumaje/"
  },
  {
    "text": "\n\n\n\n\n\n\nLa gran belleza: Roma en verano \n\nPor Rub\u00e9n Aguilar\n\n\n\n",
    "url": "https://www.animalpolitico.com/lo-que-quiso-decir/la-gran-belleza-roma-en-verano/"
  },
  {
    "text": "\n\n\n\n\n\n\n Tratado de ciencia canalla \n\nPor Eduardo Lim\u00f3n\n\n\n\n",
    "url": "https://www.animalpolitico.com/transito-lento/tratado-de-ciencia-canalla/"
  },
  {
    "text": "\n\n\n\n\n\n\nLa falsa consulta en el Senado sobre el C\u00f3digo Civil \n\nPor Yo Tambi\u00e9n\n\n\n\n",
    "url": "https://www.animalpolitico.com/yo-tambien-discapacidad-con-todas-sus-letras/la-falsa-consulta-en-el-senado-sobre-el-codigo-civil/"
  },
  {
    "text": "\n\n\n\n\n\n\n\u00bfQu\u00e9 pas\u00f3 con el multifeminicidio y homicidio en la colonia Narvarte?\u00a0 \n\nPor Art\u00edculo 19\n\n\n\n",
    "url": "https://www.animalpolitico.com/altoparlante/que-paso-con-el-multifeminicidio-y-homicidio-en-la-colonia-narvarte/"
  },
  {
    "text": "\n\n\n\n\n\n\nLa culpa es de la mujer siempre. \u00bfNeta, en serio? \n\nPor Yo Tambi\u00e9n\n\n\n\n",
    "url": "https://www.animalpolitico.com/yo-tambien-discapacidad-con-todas-sus-letras/la-culpa-es-de-la-mujer-siempre-neta-en-serio/"
  },
  {
    "text": "\n\n\n\n\n\n\nEn 2022, se rompe el r\u00e9cord de violencia \n\nPor Rub\u00e9n Aguilar\n\n\n\n",
    "url": "https://www.animalpolitico.com/lo-que-quiso-decir/en-2022-se-rompe-el-record-de-violencia/"
  },
  {
    "text": "\n\n\n\n\nGabriela L\u00f3pez y Alejandra Enr\u00edquez \n\n\n\nAnticorrupci\u00f3n, g\u00e9nero y feminismos: Gu\u00eda para Pol\u00edticas P\u00fablicas \n\nPor Blog Invitado\n\n\n\n",
    "url": "https://www.animalpolitico.com/blog-invitado/anticorrupcion-genero-y-feminismos-guia-para-politicas-publicas/"
  },
  {
    "text": "\n\n\n\n\n\n\nConversaciones tan inc\u00f3modas como necesarias \n\nPor Lexia\n\n\n\n",
    "url": "https://www.animalpolitico.com/el-blog-de-lexia/conversaciones-tan-incomodas-como-necesarias/"
  },
  {
    "text": "\n\n\n\n\n\n\nLa moratoria constitucional y la verdadera batalla por el INE \n\nPor Bernardo Le\u00f3n-Olea\n\n\n\n",
    "url": "https://www.animalpolitico.com/sociedad-abierta/la-moratoria-constitucional-y-la-verdadera-batalla-por-el-ine/"
  },
  {
    "text": "\n\n\n\n\n \n\nDespilfarro \n\nPor M\u00e9xico c\u00f3mo vamos\n\n\n\n",
    "url": "https://www.animalpolitico.com/mexico-como-vamos/despilfarro/"
  },
  {
    "text": "\n\n\n\n\n\n\n\u00bf\u2018Carte blanche\u2019 para la pol\u00edtica energ\u00e9tica? \n\nPor IMCO\n\n\n\n",
    "url": "https://www.animalpolitico.com/sin-competitividad-no-hay-paraiso/carte-blanche-para-la-politica-energetica/"
  },
  {
    "text": "\n\n\n\n\n\n\n\u00bfC\u00f3mo dar un paso hacia adelante por la lactancia materna en M\u00e9xico? \n\nPor Pacto por la Primera Infancia\n\n\n\n",
    "url": "https://www.animalpolitico.com/pacto-por-la-primera-infancia/como-dar-un-paso-hacia-adelante-por-la-lactancia-materna-en-mexico/"
  },
  {
    "text": "\nVer m\u00e1s\n",
    "url": "https://www.animalpolitico.com/plumaje/"
  },
  {
    "text": "\n\n \n\n\n\n\nDetienen al presunto feminicida de la enfermera Adriana In\u00e9s en el Edomex \n\n\n",
    "url": "https://www.animalpolitico.com/2022/07/presunto-feminicida-enfermera-adriana-ines-edomex/"
  },
  {
    "text": "\n\n \n\n\n\n\nMorena elige integrantes de Congreso Nacional entre litigios y tensiones \n\n\n",
    "url": "https://www.animalpolitico.com/2022/07/morena-elige-integrantes-congreso-nacional/"
  },
  {
    "text": "\n\n \n\n\n\n\nUn trabajador muere y otro desaparece tras incendio en refiner\u00eda de Pemex \n\n\n",
    "url": "https://www.animalpolitico.com/2022/07/trabajador-muere-otro-desaparecido-incendio-refineria-pemex/"
  },
  {
    "text": "\n\n \n\n\n\n\nBBC News Mundo \n\nPapa Francisco asegura que podr\u00eda renunciar, pero que ahora no es el momento \n\n\n",
    "url": "https://www.animalpolitico.com/bbc/papa-francisco-renunciar-no-es-momento/"
  },
  {
    "text": "\n\n \n\n\n\n\nSin medidas, la gasolina estar\u00eda en 35 pesos e inflaci\u00f3n en 11%: Hacienda \n\n\n",
    "url": "https://www.animalpolitico.com/2022/07/gasolina-inflacion-medidas-gobierno-hacienda/"
  },
  {
    "text": "\nEspeciales\n",
    "url": "https://www.animalpolitico.com/especiales/"
  },
  {
    "text": "\n\n\n",
    "url": "https://www.animalpolitico.com/techos-seguros-mujeres/"
  },
  {
    "text": "\n\n\n",
    "url": "https://www.animalpolitico.com/anexos-de-guanajuato/"
  },
  {
    "text": "\n\n\n",
    "url": "https://comercio-injusto.animalpolitico.com/"
  },
  {
    "text": "\n\n\n",
    "url": "https://www.animalpolitico.com/prision-preventiva-delitos-encarcela-pobres-inocentes/"
  },
  {
    "text": "\nVer m\u00e1s\n",
    "url": "https://www.animalpolitico.com/especiales/"
  },
  {
    "text": "\nVideo\n",
    "url": "https://www.animalpolitico.com/videos/"
  },
  {
    "text": "\n\n \n\nplay_arrow\n\n\n\n\n\nVideo \n\nDesabasto de PrEP, PEP y otros tratamientos para el VIH \n\n\n",
    "url": "https://www.animalpolitico.com/video/desabasto-de-prep-pep-y-otros-tratamientos-para-el-vih/"
  },
  {
    "text": "\n\n \n\nplay_arrow\n\n\n\n\n\nVideo \n\nEnfermedades mentales, al cuidado de los familiares \n\n\n",
    "url": "https://www.animalpolitico.com/video/enfermedades-mentales-al-cuidado-de-los-familiares/"
  },
  {
    "text": "\n\n \n\nplay_arrow\n\n\n\n\n\nVideo \n\nLas 5 secuelas m\u00e1s comunes que deja COVID-19 \n\n\n",
    "url": "https://www.animalpolitico.com/video/las-5-secuelas-mas-comunes-que-deja-covid-19/"
  },
  {
    "text": "\n\n \n\nplay_arrow\n\n\n\n\n\nVideo \n\nA mitad del sexenio y pese a promesas, persisten carencias en Salud \n\n\n",
    "url": "https://www.animalpolitico.com/video/a-mitad-del-sexenio-y-pese-a-promesas-persisten-carencias-en-salud/"
  },
  {
    "text": "\nVer m\u00e1s\n",
    "url": "https://www.animalpolitico.com/videos/"
  },
  {
    "text": "\n\n \n\n\n\n\nM\u00e9xico registra 19 mil 352 contagio de COVID y 109 muertes m\u00e1s en un d\u00eda \n\n\n",
    "url": "https://www.animalpolitico.com/2022/07/covid-mexico-19-mil-contagios-muertes-salud/"
  },
  {
    "text": "\n\n \n\n\n\n\nElecci\u00f3n Morena: denuncian acarreo, compra de voto y quema de urnas \n\n\n",
    "url": "https://www.animalpolitico.com/2022/07/eleccion-morena-denuncian-acarreo-compra-voto-quema-urnas/"
  },
  {
    "text": "\n\n \n\n\n\n\nArrestan al presunto autor material del feminicidio de Cecilia Monz\u00f3n \n\n\n",
    "url": "https://www.animalpolitico.com/2022/07/cecilia-monzon-arrestan-autor-material-feminicidio/"
  },
  {
    "text": "\n\n \n\n\n\n\nBiden da positivo a COVID por segunda ocasi\u00f3n; retomar\u00e1 estricto confinamiento \n\n\n",
    "url": "https://www.animalpolitico.com/2022/07/biden-covid-positivo-presidente-eu-confinamiento/"
  },
  {
    "text": "\n\n \n\n\n\n\nDetienen al exdirector jur\u00eddico de la BJ por presunto enriquecimiento il\u00edcito \n\n\n",
    "url": "https://www.animalpolitico.com/2022/07/detienen-exdirector-juridico-benito-juarez-enriquecimiento-ilicito/"
  },
  {
    "text": "\nHablemos de...\n",
    "url": "https://www.animalpolitico.com/hablemos-de/"
  },
  {
    "text": "\n\n \n\n\n\n\nSostenibilidad y responsabilidad social: tres pasos para hacerlos realidad \n\n\n",
    "url": "https://www.animalpolitico.com/2022/07/sostenibilidad-y-responsabilidad-social-tres-pasos-para-hacerlos-realidad/"
  },
  {
    "text": "\n\n \n\n\n\n\nA 34 a\u00f1os del primer trasplante de coraz\u00f3n en M\u00e9xico \n\n\n",
    "url": "https://www.animalpolitico.com/2022/07/a-34-anos-del-primer-trasplante-de-corazon-en-mexico/"
  },
  {
    "text": "\nVer m\u00e1s\n",
    "url": "https://www.animalpolitico.com/hablemos-de/"
  },
  {
    "text": "\n\n\n\n>\n\nBBC News Mundo:\n\nPapa Francisco asegura que podr\u00eda renunciar, pero que ahora no es el momento \n\n\n",
    "url": "https://www.animalpolitico.com/bbc/papa-francisco-renunciar-no-es-momento/"
  },
  {
    "text": "\n\n\n\n>\nSin medidas, la gasolina estar\u00eda en 35 pesos e inflaci\u00f3n en 11%: Hacienda \n\n\n",
    "url": "https://www.animalpolitico.com/2022/07/gasolina-inflacion-medidas-gobierno-hacienda/"
  },
  {
    "text": "\n\n\n\n>\n\nEl Sabueso:\n\nT-MEC: AMLO apela a la soberan\u00eda, mientras EU reclama libre competencia \n\n\n",
    "url": "https://www.animalpolitico.com/elsabueso/t-mec-soberania-amlo-eu-competencia/"
  },
  {
    "text": "\n\n\n\n>\nEconom\u00eda mexicana creci\u00f3 1% en segundo trimestre de 2022: Inegi \n\n\n",
    "url": "https://www.animalpolitico.com/2022/07/economia-mexicana-crecio-segundo-trimestre-2022-inegi/"
  },
  {
    "text": "\n\n\n\n>\nAduanas: Sedena ordena que todo el personal civil sea relevado por militares \n\n\n",
    "url": "https://www.animalpolitico.com/2022/07/aduanas-sedena-ordena-cambiar-personal-civil-por-militares/"
  },
  {
    "text": "\n\n\n\n>\nEscuela de Yucat\u00e1n suspende a ni\u00f1a que denunci\u00f3 acoso sexual de maestro \n\n\n",
    "url": "https://www.animalpolitico.com/2022/07/escuela-yucatan-nina-acoso-sexual-maestro/"
  },
  {
    "text": "\n\n\n\n>\nAnte crisis en Nuevo Le\u00f3n, gobierno lanza plan para dar agua durante 10 a\u00f1os \n\n\n",
    "url": "https://www.animalpolitico.com/2022/07/nuevo-leon-amlo-plan-abasto-agua/"
  },
  {
    "text": "\n\n\n\n>\nSalud reporta tercer d\u00eda con casos de COVID a la baja; registra 23 mil 248 \n\n\n",
    "url": "https://www.animalpolitico.com/2022/07/covid-mexico-tres-dias-casos-baja/"
  },
  {
    "text": "\n\n\n\n>\nSubsidios a gasolinas se compensan con ingresos petroleros: Hacienda \n\n\n",
    "url": "https://www.animalpolitico.com/2022/07/hacienda-subsidios-gasolinas-ingresos-petroleros-segundo-trimeste/"
  },
  {
    "text": "\n\n\n\n>\nA 2 a\u00f1os de la extradici\u00f3n de Lozoya, ni juicio ni reparaci\u00f3n del da\u00f1o \n\n\n",
    "url": "https://www.animalpolitico.com/2022/07/lozoya-dos-anos-extradicion-no-juicio-reparacion/"
  },
  {
    "text": "\n\n\n\n>\nCDMX: Ni\u00f1os de 8 a\u00f1os ser\u00e1n vacunados contra COVID la pr\u00f3xima semana \n\n\n",
    "url": "https://www.animalpolitico.com/2022/07/covid-cdmx-ninos-8-vacunados-proxima-semana/"
  },
  {
    "text": "\n\n\n\n>\nCofepris alerta sobre 44 distribuidores de medicamentos irregulares \n\n\n",
    "url": "https://www.animalpolitico.com/2022/07/cofepris-distribuidores-medicamentos-irregulares/"
  },
  {
    "text": "\n\n \n\n\n\n\nLocalizan a 98 migrantes en un tr\u00e1iler abandonado en Veracruz \n\n\n",
    "url": "https://www.animalpolitico.com/2022/07/autoridades-localizan-migrantes-en-trailer-abandonado-en-veracruz/"
  },
  {
    "text": "\n\n \n\n\n\n\nDerrame de petr\u00f3leo en Tabasco y Chiapas deja a 600 mil personas sin agua \n\n\n",
    "url": "https://www.animalpolitico.com/2022/07/derrame-petroleo-tabasco-chiapas-deja-a-personas-sin-agua/"
  },
  {
    "text": "\n\n \n\n\n\n\nCaso de Luz Raquel se usa para lucrar pol\u00edticamente: gobernador de Jalisco \n\n\n",
    "url": "https://www.animalpolitico.com/2022/07/luz-raquel-gobernador-jalisco-criticas/"
  },
  {
    "text": "\n\n",
    "url": "https://www.animalpolitico.com/ramon/"
  },
  {
    "text": "\n\"Seguridad\" ",
    "url": "https://www.animalpolitico.com/ramon/seguridad/"
  },
  {
    "text": "\n\n",
    "url": "https://api.whatsapp.com/send?text=%22Seguridad%22+https%3A%2F%2Fwww.animalpolitico.com%2Framon%2Fseguridad%2F"
  },
  {
    "text": "\n\n",
    "url": "https://www.facebook.com/sharer/sharer.php?u=https%3A%2F%2Fwww.animalpolitico.com%2Framon%2Fseguridad%2F"
  },
  {
    "text": "\n\n",
    "url": "mailto:?subject=%22Seguridad%22&body=https%3A%2F%2Fwww.animalpolitico.com%2Framon%2Fseguridad%2F"
  },
  {
    "text": "\n\n",
    "url": "https://twitter.com/intent/tweet?url=https%3A%2F%2Fwww.animalpolitico.com%2Framon%2Fseguridad%2F&via=pajaropolitico&text=%22Seguridad%22"
  },
  {
    "text": "\nVer m\u00e1s Ram\u00f3n\n",
    "url": "https://www.animalpolitico.com/ramon/"
  },
  {
    "text": "\n\n",
    "url": "https://www.animalpolitico.com"
  },
  {
    "text": "\n\n",
    "url": "https://www.facebook.com/pajaropolitico"
  },
  {
    "text": "\n\n",
    "url": "https://twitter.com/pajaropolitico"
  },
  {
    "text": "\n\n",
    "url": "https://www.youtube.com/user/pajaropolitico2012"
  },
  {
    "text": "\n\n",
    "url": "https://www.instagram.com/pajaropolitico/"
  },
  {
    "text": "\n\n",
    "url": "https://flipboard.com/@AnimalPolitico"
  },
  {
    "text": "\nQui\u00e9nes Somos ",
    "url": "https://www.animalpolitico.com/quienes-somos/"
  },
  {
    "text": "\nAviso de privacidad ",
    "url": "https://www.animalpolitico.com/aviso-privacidad/"
  },
  {
    "text": "\nC\u00f3digo de \u00c9tica ",
    "url": "https://www.animalpolitico.com/codigo-de-etica/"
  },
  {
    "text": "\nAn\u00fanciate con nosotros ",
    "url": "https://www.animalpolitico.com/anunciate/"
  },
  {
    "text": "\n\n",
    "url": "https://editorialcriterio.com/media/grupo.pdf"
  },
  {
    "text": "\n\n",
    "url": "https://animalpolitico.com/suscribete?utm_source=pp2"
  }
]
