[
  {
    "text": "\n\t\t\t\t\t\t\t\n\t\t\t\t\t\t",
    "url": "https://9to5mac.com/"
  },
  {
    "text": "Exclusives",
    "url": "https://9to5mac.com/feature/exclusive/"
  },
  {
    "text": "Store",
    "url": "https://www.9to5mac.com/store"
  },
  {
    "text": "Guides",
    "url": "http://9to5mac.com/guides"
  },
  {
    "text": "Reviews",
    "url": "https://9to5mac.com/guides/review/"
  },
  {
    "text": "How Tos",
    "url": "https://9to5mac.com/guides/how-to/"
  },
  {
    "text": "AAPL",
    "url": "https://9to5mac.com/guides/aapl/"
  },
  {
    "text": "Apple Store",
    "url": "https://9to5mac.com/guides/apple-store/"
  },
  {
    "text": "Apple Arcade",
    "url": "https://9to5mac.com/guides/apple-arcade/"
  },
  {
    "text": "Apple Card",
    "url": "https://9to5mac.com/guides/apple-card/"
  },
  {
    "text": "Apple Silicon",
    "url": "https://9to5mac.com/guides/apple-silicon/"
  },
  {
    "text": "Apple One",
    "url": "https://9to5mac.com/guides/apple-one/"
  },
  {
    "text": "CarPlay",
    "url": "https://9to5mac.com/guides/carplay/"
  },
  {
    "text": "Siri",
    "url": "https://9to5mac.com/guides/siri/"
  },
  {
    "text": "HomeKit",
    "url": "https://9to5mac.com/guides/homekit/"
  },
  {
    "text": "Mac",
    "url": "https://9to5mac.com/guides/mac/"
  },
  {
    "text": "Mac",
    "url": "https://9to5mac.com/guides/mac/"
  },
  {
    "text": "MacBook Pro",
    "url": "https://9to5mac.com/guides/macbook-pro/"
  },
  {
    "text": "MacBook Air",
    "url": "https://9to5mac.com/guides/macbook-air/"
  },
  {
    "text": "iMac 2021",
    "url": "https://9to5mac.com/guides/imac-2021/"
  },
  {
    "text": "iMac",
    "url": "https://9to5mac.com/guides/imac/"
  },
  {
    "text": "Mac Pro",
    "url": "https://9to5mac.com/guides/mac-pro/"
  },
  {
    "text": "Mac mini",
    "url": "https://9to5mac.com/guides/mac-mini/"
  },
  {
    "text": "macOS Monterey",
    "url": "http://9to5mac.com/guides/macos-monterey"
  },
  {
    "text": "iPhone",
    "url": "https://9to5mac.com/guides/iphone/"
  },
  {
    "text": "iPhone",
    "url": "https://9to5mac.com/guides/iphone/"
  },
  {
    "text": "iPhone 11",
    "url": "https://9to5mac.com/guides/iphone-11/"
  },
  {
    "text": "iPhone 12",
    "url": "https://9to5mac.com/guides/iphone-12/"
  },
  {
    "text": "iPhone 13",
    "url": "https://9to5mac.com/guides/iphone-13/"
  },
  {
    "text": "iOS 15",
    "url": "https://9to5mac.com/guides/ios-15/"
  },
  {
    "text": "Watch",
    "url": "https://9to5mac.com/guides/apple-watch/"
  },
  {
    "text": "Apple Watch",
    "url": "https://9to5mac.com/guides/apple-watch/"
  },
  {
    "text": "Apple Health",
    "url": "https://9to5mac.com/guides/apple-health/"
  },
  {
    "text": "Apple Watch Series 7",
    "url": "https://9to5mac.com/guides/apple-watch-series-7/"
  },
  {
    "text": "Apple Watch SE",
    "url": "https://9to5mac.com/guides/apple-watch-se/"
  },
  {
    "text": "Apple Watch Series 3",
    "url": "https://9to5mac.com/guides/apple-watch-series-3/"
  },
  {
    "text": "watchOS 8",
    "url": "http://9to5mac.com/guides/watchos-8"
  },
  {
    "text": "Apple Fitness+",
    "url": "https://9to5mac.com/guides/apple-fitness/"
  },
  {
    "text": "iPad",
    "url": "https://9to5mac.com/guides/ipad/"
  },
  {
    "text": "iPad Pro",
    "url": "https://9to5mac.com/guides/ipad-pro/"
  },
  {
    "text": "iPad Air",
    "url": "https://9to5mac.com/guides/ipad-air/"
  },
  {
    "text": "iPad mini",
    "url": "https://9to5mac.com/guides/ipad-mini/"
  },
  {
    "text": "iPad",
    "url": "https://9to5mac.com/guides/ipad/"
  },
  {
    "text": "iPadOS",
    "url": "http://9to5mac.com/guides/ipados"
  },
  {
    "text": "Music",
    "url": "https://9to5mac.com/guides/apple-music/"
  },
  {
    "text": "Apple Music",
    "url": "https://9to5mac.com/guides/apple-music/"
  },
  {
    "text": "AirPods",
    "url": "https://9to5mac.com/guides/airpods/"
  },
  {
    "text": "HomePod",
    "url": "https://9to5mac.com/guides/homepod/"
  },
  {
    "text": "TV",
    "url": "https://9to5mac.com/guides/apple-tv/"
  },
  {
    "text": "Apple TV 4K",
    "url": "https://9to5mac.com/guides/apple-tv-4k/"
  },
  {
    "text": "Apple TV",
    "url": "https://9to5mac.com/guides/apple-tv/"
  },
  {
    "text": "tvOS 15",
    "url": "http://9to5mac.com/guides/tvos-15"
  },
  {
    "text": "\n\t\t\n\t\t\t\t\t\t\t\t\t\n\t\t\n\t\t",
    "url": "https://www.youtube.com/c/9to5mac"
  },
  {
    "text": "\n\t\t\n\t\t\t\t\t\t\t\t\t\n\t\t\n\t\t",
    "url": "https://www.facebook.com/9to5mac/"
  },
  {
    "text": "\n\t\t\n\t\t\t\t\t\t\t\t\t\n\t\t\n\t\t",
    "url": "http://twitter.com/9to5mac"
  },
  {
    "text": "\n\t\t\n\t\t\t\t\t\t\t\t\t\n\t\t\n\t\t",
    "url": "https://instagram.com/9to5mac"
  },
  {
    "text": "\n\t\t\n\t\t\t\t\t\t\t\t\t\n\t\t\n\t\t",
    "url": "https://9to5mac.com/guides/podcast/"
  },
  {
    "text": "\n\t\t\n\t\t\t\t\t\t\t\t\t\n\t\t\n\t\t",
    "url": "https://apple.news/THIO8RUsFTaaGHbdNl6KqOQ"
  },
  {
    "text": "\n\t\t\n\t\t\t\t\t\t\t\t\t\n\t\t\n\t\t",
    "url": "https://www.linkedin.com/company/9to5mac.com"
  },
  {
    "text": "\n\t\t\n\t\t\t\t\t\t\t\t\t\n\t\t\n\t\t",
    "url": "https://9to5mac.com/push/"
  },
  {
    "text": "\n\t\t\n\t\t\t\t\t\t\t\t\t\n\t\t\n\t\t",
    "url": "https://9to5mac.com/9to5mac-newsletter-signup/"
  },
  {
    "text": "\t\t\n\t\t\t\t\t\t\t\t\t\n\t\t\n\t\tSubmit a Tip / Contact Us",
    "url": "https://9to5mac.com/contact/"
  },
  {
    "text": "\t\t\n\t\t\t\t\t\t\t\t\t\n\t\t\n\t\tCashback",
    "url": "https://www.decluttr.com/9to5mac?utm_campaign=9to5mac&utm_medium=referral&utm_source=9to5mac&utm_term=&utm_content=#tradein"
  },
  {
    "text": "\t\t\n\t\t\t\t\t\t\t\t\t\n\t\t\n\t\tFix",
    "url": "https://9to5mac.ifixyouri.com"
  },
  {
    "text": "\t\t\n\t\t\t\t\t\t\t\t\t\n\t\t\n\t\t9to5Toys",
    "url": "https://9to5toys.com"
  },
  {
    "text": "\t\t\n\t\t\t\t\t\t\t\t\t\n\t\t\n\t\t9to5Google",
    "url": "https://9to5google.com"
  },
  {
    "text": "Electrek",
    "url": "https://electrek.co"
  },
  {
    "text": "DroneDJ",
    "url": "https://www.dronedj.com"
  },
  {
    "text": "\t\t\n\t\t\t\t\t\t\t\t\t\n\t\t\n\t\tSpace Explored",
    "url": "https://www.spaceexplored.com"
  },
  {
    "text": "About",
    "url": "https://9to5mac.com/about/"
  },
  {
    "text": "Privacy",
    "url": "https://9to5mac.com/privacy/"
  },
  {
    "text": "\n\t\t\t\t\t\n\t\t\t\t\t\t\n\t\t\t\t\t\t\n\t\t\t\t\t\t\t\n\t\t\t\t\t\t\t\t\n\t\t\t\t\t\t\t\tApple reports record Q3 2022 earnings\n\t\t\t\t\t\t\t\t\n\t\t\t\t\t\t\t\t\t\n\t\t\t\t\t\t\t\n\t\t\t\t\t\t\n\t\t\t\t\t\n\t\t\t\t",
    "url": "https://9to5mac.com/2022/07/28/apple-q3-2022-earnings/"
  },
  {
    "text": "\n\t\t\t\t\t\n\t\t\t\t\t\t\n\t\t\t\t\t\t\n\t\t\t\t\t\t\t\n\t\t\t\t\t\t\t\t\n\t\t\t\t\t\t\t\tiPhone 14 Pro always-on screen behavior previewed\n\t\t\t\t\t\t\t\t\n\t\t\t\t\t\t\t\t\t\n\t\t\t\t\t\t\t\n\t\t\t\t\t\t\n\t\t\t\t\t\n\t\t\t\t",
    "url": "https://9to5mac.com/2022/07/28/iphone-14-pro-always-on-ios-16-wallpaper/"
  },
  {
    "text": "\n\t\t\t\t\t\n\t\t\t\t\t\t\n\t\t\t\t\t\t\n\t\t\t\t\t\t\t\n\t\t\t\t\t\t\t\t\n\t\t\t\t\t\t\t\tSubscribe to 9to5Mac Daily!\n\t\t\t\t\t\t\t\t\n\t\t\t\t\t\t\t\t\t\n\t\t\t\t\t\t\t\n\t\t\t\t\t\t\n\t\t\t\t\t\n\t\t\t\t",
    "url": "https://9to5mac.com/2022/07/28/9to5mac-daily-july-28-2022/"
  },
  {
    "text": "\n\t\t\t\t\t\n\t\t\t\t\t\t\n\t\t\t\t\t\t\n\t\t\t\t\t\t\t\n\t\t\t\t\t\t\t\t\n\t\t\t\t\t\t\t\tHands-on: Stage Manager for iPad [Video]\n\t\t\t\t\t\t\t\t\n\t\t\t\t\t\t\t\t\t\n\t\t\t\t\t\t\t\n\t\t\t\t\t\t\n\t\t\t\t\t\n\t\t\t\t",
    "url": "https://9to5mac.com/2022/07/28/stage-manager-on-ipad/"
  },
  {
    "text": "Hands-on: CardPointers maximizes your credit card rewards with iPhone, iPad, and Mac apps",
    "url": "https://9to5mac.com/2022/07/29/hands-on-cardpointers-maximizes-your-credit-card-rewards-with-iphone-ipad-and-mac-apps/"
  },
  {
    "text": "\n\t\t\t\t\t\t\t\tChance Miller\n\t\t\t\t\t\t\t",
    "url": "https://9to5mac.com/author/chmiller44/"
  },
  {
    "text": "@ChanceHMiller",
    "url": "https://twitter.com/intent/follow?screen_name=ChanceHMiller&original_referer=https%3A%2F%2F9to5mac.com"
  },
  {
    "text": "iOS",
    "url": "https://9to5mac.com/guides/ios/"
  },
  {
    "text": "\n\t\t\t\t\t\t\t\t\n\t\t\t\t\t\t\t",
    "url": "https://9to5mac.com/2022/07/29/hands-on-cardpointers-maximizes-your-credit-card-rewards-with-iphone-ipad-and-mac-apps/"
  },
  {
    "text": "Add Your Comment",
    "url": "https://9to5mac.com/2022/07/29/hands-on-cardpointers-maximizes-your-credit-card-rewards-with-iphone-ipad-and-mac-apps/#disqus_thread"
  },
  {
    "text": "Facebook",
    "url": "https://9to5mac.com/2022/07/29/hands-on-cardpointers-maximizes-your-credit-card-rewards-with-iphone-ipad-and-mac-apps/?share=facebook"
  },
  {
    "text": "Twitter",
    "url": "https://9to5mac.com/2022/07/29/hands-on-cardpointers-maximizes-your-credit-card-rewards-with-iphone-ipad-and-mac-apps/?share=twitter"
  },
  {
    "text": "Pinterest",
    "url": "https://9to5mac.com/2022/07/29/hands-on-cardpointers-maximizes-your-credit-card-rewards-with-iphone-ipad-and-mac-apps/?share=pinterest"
  },
  {
    "text": "LinkedIn",
    "url": "https://9to5mac.com/2022/07/29/hands-on-cardpointers-maximizes-your-credit-card-rewards-with-iphone-ipad-and-mac-apps/?share=linkedin"
  },
  {
    "text": "Reddit",
    "url": "https://9to5mac.com/2022/07/29/hands-on-cardpointers-maximizes-your-credit-card-rewards-with-iphone-ipad-and-mac-apps/?share=reddit"
  },
  {
    "text": "CardPointers",
    "url": "https://cardpointers.com/partner/925/"
  },
  {
    "text": "exclusive discount and offer",
    "url": "https://cardpointers.com/partner/925/"
  },
  {
    "text": "expand full story ",
    "url": "https://9to5mac.com/2022/07/29/hands-on-cardpointers-maximizes-your-credit-card-rewards-with-iphone-ipad-and-mac-apps/#more-824094"
  },
  {
    "text": "9to5Rewards Last Chance: Win a Mac Studio and a 14-inch MacBook Pro from Mosyle",
    "url": "https://9to5mac.com/2022/07/29/9to5rewards-last-chance-win-a-mac-studio-and-a-14-inch-macbook-pro-from-mosyle/"
  },
  {
    "text": "\n\t\t\t\t\t\t\t\tSponsored Post\n\t\t\t\t\t\t\t",
    "url": "https://9to5mac.com/author/sponsoredpostz/"
  },
  {
    "text": "9to5Rewards",
    "url": "https://9to5mac.com/guides/9to5rewards/"
  },
  {
    "text": "\n\t\t\t\t\t\t\t\t\n\t\t\t\t\t\t\t",
    "url": "https://9to5mac.com/2022/07/29/9to5rewards-last-chance-win-a-mac-studio-and-a-14-inch-macbook-pro-from-mosyle/"
  },
  {
    "text": "Add Your Comment",
    "url": "https://9to5mac.com/2022/07/29/9to5rewards-last-chance-win-a-mac-studio-and-a-14-inch-macbook-pro-from-mosyle/#disqus_thread"
  },
  {
    "text": "Facebook",
    "url": "https://9to5mac.com/2022/07/29/9to5rewards-last-chance-win-a-mac-studio-and-a-14-inch-macbook-pro-from-mosyle/?share=facebook"
  },
  {
    "text": "Twitter",
    "url": "https://9to5mac.com/2022/07/29/9to5rewards-last-chance-win-a-mac-studio-and-a-14-inch-macbook-pro-from-mosyle/?share=twitter"
  },
  {
    "text": "Pinterest",
    "url": "https://9to5mac.com/2022/07/29/9to5rewards-last-chance-win-a-mac-studio-and-a-14-inch-macbook-pro-from-mosyle/?share=pinterest"
  },
  {
    "text": "LinkedIn",
    "url": "https://9to5mac.com/2022/07/29/9to5rewards-last-chance-win-a-mac-studio-and-a-14-inch-macbook-pro-from-mosyle/?share=linkedin"
  },
  {
    "text": "Reddit",
    "url": "https://9to5mac.com/2022/07/29/9to5rewards-last-chance-win-a-mac-studio-and-a-14-inch-macbook-pro-from-mosyle/?share=reddit"
  },
  {
    "text": "Mosyle",
    "url": "https://mosyle.net/e0e5"
  },
  {
    "text": "Mosyle\u2019s Apple Unified Platform for Business",
    "url": "https://mosyle.net/e0e5"
  },
  {
    "text": "expand full story ",
    "url": "https://9to5mac.com/2022/07/29/9to5rewards-last-chance-win-a-mac-studio-and-a-14-inch-macbook-pro-from-mosyle/#more-824285"
  },
  {
    "text": "Apple blasts Android malware in fierce pushback against iOS sideloading",
    "url": "https://9to5mac.com/2022/07/29/iphone-sideloading-malware-android/"
  },
  {
    "text": "\n\t\t\t\t\t\t\t\tChance Miller\n\t\t\t\t\t\t\t",
    "url": "https://9to5mac.com/author/chmiller44/"
  },
  {
    "text": "@ChanceHMiller",
    "url": "https://twitter.com/intent/follow?screen_name=ChanceHMiller&original_referer=https%3A%2F%2F9to5mac.com"
  },
  {
    "text": "App Store",
    "url": "https://9to5mac.com/guides/app-store/"
  },
  {
    "text": "\n\t\t\t\t\t\t\t\t\n\t\t\t\t\t\t\t",
    "url": "https://9to5mac.com/2022/07/29/iphone-sideloading-malware-android/"
  },
  {
    "text": "39 Comments",
    "url": "https://9to5mac.com/2022/07/29/iphone-sideloading-malware-android/#disqus_thread"
  },
  {
    "text": "Facebook",
    "url": "https://9to5mac.com/2022/07/29/iphone-sideloading-malware-android/?share=facebook"
  },
  {
    "text": "Twitter",
    "url": "https://9to5mac.com/2022/07/29/iphone-sideloading-malware-android/?share=twitter"
  },
  {
    "text": "Pinterest",
    "url": "https://9to5mac.com/2022/07/29/iphone-sideloading-malware-android/?share=pinterest"
  },
  {
    "text": "LinkedIn",
    "url": "https://9to5mac.com/2022/07/29/iphone-sideloading-malware-android/?share=linkedin"
  },
  {
    "text": "Reddit",
    "url": "https://9to5mac.com/2022/07/29/iphone-sideloading-malware-android/?share=reddit"
  },
  {
    "text": "looming antitrust legislation in the United States",
    "url": "https://9to5mac.com/2022/02/03/app-store-open-markets-act-senate-advance/"
  },
  {
    "text": "expand full story ",
    "url": "https://9to5mac.com/2022/07/29/iphone-sideloading-malware-android/#more-824226"
  },
  {
    "text": "Electrek\u00a0",
    "url": "https://electrek.co"
  },
  {
    "text": "",
    "url": "https://www.facebook.com/electrekco"
  },
  {
    "text": "",
    "url": "http://twitter.com/electrekco"
  },
  {
    "text": "",
    "url": "https://www.youtube.com/c/electrekco?sub_confirmation=1"
  },
  {
    "text": "\n\t\t\t\t\t\t\t\t\t\n\t\t\t\t\t\t\t\t\t\t\n\t\t\t\t\t\t\t\t\t\n\t\t\t\t\t\t\t\t",
    "url": "https://itunes.apple.com/us/podcast/electrek/id1320055779"
  },
  {
    "text": "\n\t\t\t\t\t\t\t\t\t\n\t\t\t\t\t\t\t\t\t\t\n\t\t\t\t\t\t\t\t\t\n\t\t\t\t\t\t\t\t",
    "url": "https://eepurl.com/bTzCKT"
  },
  {
    "text": "\n\t\t\t\t\t\t\t\t\n\t\t\t\t\t\t\t\t2023 Chevy Bolt EV is still the best value EV in America, by far\n\t\t\t\t\t\t\t",
    "url": "https://electrek.co/2022/07/29/2023-chevy-bolt-ev/"
  },
  {
    "text": "\n\t\t\t\t\t\t\t\t\n\t\t\t\t\t\t\t\tPodcast: Tesla Supercharger Cube lounge, new EV federal credit, Mercedes-Benz EQXX, and more\n\t\t\t\t\t\t\t",
    "url": "https://electrek.co/2022/07/29/podcast-tesla-supercharger-cube-lounge-new-ev-federal-credit-mercedes-benz-eqxx/"
  },
  {
    "text": "\n\t\t\t\t\t\t\t\t\n\t\t\t\t\t\t\t\tThis company is buying 200 Tesla vehicles per week and is now ordering 23,000 EVs\n\t\t\t\t\t\t\t",
    "url": "https://electrek.co/2022/07/29/autonomy-buying-200-tesla-vehicles-per-week-ordering-23000-evs/"
  },
  {
    "text": "\n\t\t\t\t\t\t\t\t\n\t\t\t\t\t\t\t\tBLACK+DECKER blower/vacuum/mulcher cleans your yard ahead of fall at $67 in New Green Deals\n\t\t\t\t\t\t\t",
    "url": "https://electrek.co/2022/07/29/black-decker-blower-vacuum-combo-more-new-green-deals/"
  },
  {
    "text": "\n\t\t\t\t\t\t\t\t\n\t\t\t\t\t\t\t\tElectric trucks like Tesla Semi will get up to $40,000 in incentives with new bill\n\t\t\t\t\t\t\t",
    "url": "https://electrek.co/2022/07/29/electric-trucks-tesla-semi-40000-incentives-new-bill/"
  },
  {
    "text": "Track medications on iPhone: How the new iOS 16 feature works",
    "url": "https://9to5mac.com/2022/07/29/track-medications-on-iphone/"
  },
  {
    "text": "\n\t\t\t\t\t\t\t\tMichael Potuck\n\t\t\t\t\t\t\t",
    "url": "https://9to5mac.com/author/michaelpotuck/"
  },
  {
    "text": "@michaelpotuck",
    "url": "https://twitter.com/intent/follow?screen_name=michaelpotuck&original_referer=https%3A%2F%2F9to5mac.com"
  },
  {
    "text": "iPhone",
    "url": "https://9to5mac.com/guides/iphone/"
  },
  {
    "text": "How-to",
    "url": "https://9to5mac.com/guides/how-to/"
  },
  {
    "text": "Apple Health",
    "url": "https://9to5mac.com/guides/apple-health/"
  },
  {
    "text": "iOS 16",
    "url": "https://9to5mac.com/guides/ios-16/"
  },
  {
    "text": "\n\t\t\t\t\t\t\t\t\n\t\t\t\t\t\t\t",
    "url": "https://9to5mac.com/2022/07/29/track-medications-on-iphone/"
  },
  {
    "text": "5 Comments",
    "url": "https://9to5mac.com/2022/07/29/track-medications-on-iphone/#disqus_thread"
  },
  {
    "text": "Facebook",
    "url": "https://9to5mac.com/2022/07/29/track-medications-on-iphone/?share=facebook"
  },
  {
    "text": "Twitter",
    "url": "https://9to5mac.com/2022/07/29/track-medications-on-iphone/?share=twitter"
  },
  {
    "text": "Pinterest",
    "url": "https://9to5mac.com/2022/07/29/track-medications-on-iphone/?share=pinterest"
  },
  {
    "text": "LinkedIn",
    "url": "https://9to5mac.com/2022/07/29/track-medications-on-iphone/?share=linkedin"
  },
  {
    "text": "Reddit",
    "url": "https://9to5mac.com/2022/07/29/track-medications-on-iphone/?share=reddit"
  },
  {
    "text": "expand full story ",
    "url": "https://9to5mac.com/2022/07/29/track-medications-on-iphone/#more-817301"
  },
  {
    "text": "\u2018TV Remote\u2019 app updated with theme options, custom layout, and more",
    "url": "https://9to5mac.com/2022/07/29/tv-remote-app-updated-with-theme-options-custom-layout-and-more/"
  },
  {
    "text": "\n\t\t\t\t\t\t\t\tFilipe Esp\u00f3sito\n\t\t\t\t\t\t\t",
    "url": "https://9to5mac.com/author/filipeesposito/"
  },
  {
    "text": "@filipeesposito",
    "url": "https://twitter.com/intent/follow?screen_name=filipeesposito&original_referer=https%3A%2F%2F9to5mac.com"
  },
  {
    "text": "Apps & Updates",
    "url": "https://9to5mac.com/guides/apps-updates/"
  },
  {
    "text": "\n\t\t\t\t\t\t\t\t\n\t\t\t\t\t\t\t",
    "url": "https://9to5mac.com/2022/07/29/tv-remote-app-updated-with-theme-options-custom-layout-and-more/"
  },
  {
    "text": "6 Comments",
    "url": "https://9to5mac.com/2022/07/29/tv-remote-app-updated-with-theme-options-custom-layout-and-more/#disqus_thread"
  },
  {
    "text": "Facebook",
    "url": "https://9to5mac.com/2022/07/29/tv-remote-app-updated-with-theme-options-custom-layout-and-more/?share=facebook"
  },
  {
    "text": "Twitter",
    "url": "https://9to5mac.com/2022/07/29/tv-remote-app-updated-with-theme-options-custom-layout-and-more/?share=twitter"
  },
  {
    "text": "Pinterest",
    "url": "https://9to5mac.com/2022/07/29/tv-remote-app-updated-with-theme-options-custom-layout-and-more/?share=pinterest"
  },
  {
    "text": "LinkedIn",
    "url": "https://9to5mac.com/2022/07/29/tv-remote-app-updated-with-theme-options-custom-layout-and-more/?share=linkedin"
  },
  {
    "text": "Reddit",
    "url": "https://9to5mac.com/2022/07/29/tv-remote-app-updated-with-theme-options-custom-layout-and-more/?share=reddit"
  },
  {
    "text": "TV Remote",
    "url": "https://9to5mac.com/2021/01/07/tv-remote-is-an-app-that-turns-your-iphone-into-a-universal-control-for-your-tv/"
  },
  {
    "text": "expand full story ",
    "url": "https://9to5mac.com/2022/07/29/tv-remote-app-updated-with-theme-options-custom-layout-and-more/#more-824210"
  },
  {
    "text": "Disney+ brings Dolby Atmos Spatial Audio to Apple TV 4K on original HomePods, AirPods, and more",
    "url": "https://9to5mac.com/2022/07/29/disney-dolby-atmos-apple-tv-4k/"
  },
  {
    "text": "\n\t\t\t\t\t\t\t\tMichael Potuck\n\t\t\t\t\t\t\t",
    "url": "https://9to5mac.com/author/michaelpotuck/"
  },
  {
    "text": "@michaelpotuck",
    "url": "https://twitter.com/intent/follow?screen_name=michaelpotuck&original_referer=https%3A%2F%2F9to5mac.com"
  },
  {
    "text": "Disney",
    "url": "https://9to5mac.com/guides/disney/"
  },
  {
    "text": "Spatial Audio",
    "url": "https://9to5mac.com/guides/spatial-audio/"
  },
  {
    "text": "\n\t\t\t\t\t\t\t\t\n\t\t\t\t\t\t\t",
    "url": "https://9to5mac.com/2022/07/29/disney-dolby-atmos-apple-tv-4k/"
  },
  {
    "text": "5 Comments",
    "url": "https://9to5mac.com/2022/07/29/disney-dolby-atmos-apple-tv-4k/#disqus_thread"
  },
  {
    "text": "Facebook",
    "url": "https://9to5mac.com/2022/07/29/disney-dolby-atmos-apple-tv-4k/?share=facebook"
  },
  {
    "text": "Twitter",
    "url": "https://9to5mac.com/2022/07/29/disney-dolby-atmos-apple-tv-4k/?share=twitter"
  },
  {
    "text": "Pinterest",
    "url": "https://9to5mac.com/2022/07/29/disney-dolby-atmos-apple-tv-4k/?share=pinterest"
  },
  {
    "text": "LinkedIn",
    "url": "https://9to5mac.com/2022/07/29/disney-dolby-atmos-apple-tv-4k/?share=linkedin"
  },
  {
    "text": "Reddit",
    "url": "https://9to5mac.com/2022/07/29/disney-dolby-atmos-apple-tv-4k/?share=reddit"
  },
  {
    "text": "Disney+",
    "url": "https://9to5mac.com/guides/disney/"
  },
  {
    "text": "expand full story ",
    "url": "https://9to5mac.com/2022/07/29/disney-dolby-atmos-apple-tv-4k/#more-824166"
  },
  {
    "text": "Space Explored\u00a0",
    "url": "https://spaceexplored.com"
  },
  {
    "text": "",
    "url": "https://www.facebook.com/spaceexplored/"
  },
  {
    "text": "",
    "url": "https://twitter.com/space_explored"
  },
  {
    "text": "\n\t\t\t\t\t\t\t\t\n\t\t\t\t\t\t\t\tSpaceX makes renewed effort to protect the night sky\n\t\t\t\t\t\t\t",
    "url": "https://spaceexplored.com/2022/07/29/spacex-makes-renewed-effort-to-protect-the-night-sky/"
  },
  {
    "text": "\n\t\t\t\t\t\t\t\t\n\t\t\t\t\t\t\t\tSpace junk, believed to be from Crew-1\u2019s trunk, crash lands in Australia sheep farm\n\t\t\t\t\t\t\t",
    "url": "https://spaceexplored.com/2022/07/29/space-junk-crash-lands-in-australia-sheep-farm/"
  },
  {
    "text": "\n\t\t\t\t\t\t\t\t\n\t\t\t\t\t\t\t\tStarliner\u2019s spaceship growing pains have cost Boeing nearly $700 million more than planned\n\t\t\t\t\t\t\t",
    "url": "https://spaceexplored.com/2022/07/28/boeing-starliner-cost-overrun/"
  },
  {
    "text": "\n\t\t\t\t\t\t\t\t\n\t\t\t\t\t\t\t\tHan Solo\u2019s blaster from the original \u2018Star Wars\u2019 film could soon be yours\n\t\t\t\t\t\t\t",
    "url": "https://spaceexplored.com/2022/07/28/han-solo-blaster/"
  },
  {
    "text": "\n\t\t\t\t\t\t\t\t\n\t\t\t\t\t\t\t\tNASA\u2019s Mars Sample Return mission adds two helicopters after Ingenuity flights\n\t\t\t\t\t\t\t",
    "url": "https://spaceexplored.com/2022/07/27/mars-sample-return-helicopters/"
  },
  {
    "text": "9to5Mac Happy Hour 392: iOS 16 beta 4 changes, more Apple Watch Pro info, and AR\u2019s uncertain future",
    "url": "https://9to5mac.com/2022/07/29/9to5mac-happy-hour-392-ios-16-beta-4-changes-more-apple-watch-pro-info-and-ars-uncertain-future/"
  },
  {
    "text": "\n\t\t\t\t\t\t\t\tSeth Kurkowski\n\t\t\t\t\t\t\t",
    "url": "https://9to5mac.com/author/sethkurk/"
  },
  {
    "text": "@SethKurk",
    "url": "https://twitter.com/intent/follow?screen_name=SethKurk&original_referer=https%3A%2F%2F9to5mac.com"
  },
  {
    "text": "9to5Mac Podcast Network",
    "url": "https://9to5mac.com/guides/podcast/"
  },
  {
    "text": "9to5Mac Happy Hour",
    "url": "https://9to5mac.com/guides/9to5mac-happy-hour/"
  },
  {
    "text": "\n\t\t\t\t\t\t\t\t\n\t\t\t\t\t\t\t",
    "url": "https://9to5mac.com/2022/07/29/9to5mac-happy-hour-392-ios-16-beta-4-changes-more-apple-watch-pro-info-and-ars-uncertain-future/"
  },
  {
    "text": "Add Your Comment",
    "url": "https://9to5mac.com/2022/07/29/9to5mac-happy-hour-392-ios-16-beta-4-changes-more-apple-watch-pro-info-and-ars-uncertain-future/#disqus_thread"
  },
  {
    "text": "Facebook",
    "url": "https://9to5mac.com/2022/07/29/9to5mac-happy-hour-392-ios-16-beta-4-changes-more-apple-watch-pro-info-and-ars-uncertain-future/?share=facebook"
  },
  {
    "text": "Twitter",
    "url": "https://9to5mac.com/2022/07/29/9to5mac-happy-hour-392-ios-16-beta-4-changes-more-apple-watch-pro-info-and-ars-uncertain-future/?share=twitter"
  },
  {
    "text": "Pinterest",
    "url": "https://9to5mac.com/2022/07/29/9to5mac-happy-hour-392-ios-16-beta-4-changes-more-apple-watch-pro-info-and-ars-uncertain-future/?share=pinterest"
  },
  {
    "text": "LinkedIn",
    "url": "https://9to5mac.com/2022/07/29/9to5mac-happy-hour-392-ios-16-beta-4-changes-more-apple-watch-pro-info-and-ars-uncertain-future/?share=linkedin"
  },
  {
    "text": "Reddit",
    "url": "https://9to5mac.com/2022/07/29/9to5mac-happy-hour-392-ios-16-beta-4-changes-more-apple-watch-pro-info-and-ars-uncertain-future/?share=reddit"
  },
  {
    "text": "Sponsored by Pillow",
    "url": "https://bit.ly/33MKRIP"
  },
  {
    "text": "from the App Store today",
    "url": "https://apple.co/33IkIe7"
  },
  {
    "text": "Sponsored by LinkedIn Jobs:",
    "url": "https://linkedin.com/HAPPYHOUR"
  },
  {
    "text": "LinkedIn.com/HAPPYHOUR",
    "url": "https://linkedin.com/HAPPYHOUR"
  },
  {
    "text": "expand full story ",
    "url": "https://9to5mac.com/2022/07/29/9to5mac-happy-hour-392-ios-16-beta-4-changes-more-apple-watch-pro-info-and-ars-uncertain-future/#more-824165"
  },
  {
    "text": "Apple expanding App Store ads from search to \u2018Today\u2019 tab and more",
    "url": "https://9to5mac.com/2022/07/29/app-store-ads-expanding/"
  },
  {
    "text": "\n\t\t\t\t\t\t\t\tChance Miller\n\t\t\t\t\t\t\t",
    "url": "https://9to5mac.com/author/chmiller44/"
  },
  {
    "text": "@ChanceHMiller",
    "url": "https://twitter.com/intent/follow?screen_name=ChanceHMiller&original_referer=https%3A%2F%2F9to5mac.com"
  },
  {
    "text": "App Store",
    "url": "https://9to5mac.com/guides/app-store/"
  },
  {
    "text": "\n\t\t\t\t\t\t\t\t\n\t\t\t\t\t\t\t",
    "url": "https://9to5mac.com/2022/07/29/app-store-ads-expanding/"
  },
  {
    "text": "1 Comment",
    "url": "https://9to5mac.com/2022/07/29/app-store-ads-expanding/#disqus_thread"
  },
  {
    "text": "Facebook",
    "url": "https://9to5mac.com/2022/07/29/app-store-ads-expanding/?share=facebook"
  },
  {
    "text": "Twitter",
    "url": "https://9to5mac.com/2022/07/29/app-store-ads-expanding/?share=twitter"
  },
  {
    "text": "Pinterest",
    "url": "https://9to5mac.com/2022/07/29/app-store-ads-expanding/?share=pinterest"
  },
  {
    "text": "LinkedIn",
    "url": "https://9to5mac.com/2022/07/29/app-store-ads-expanding/?share=linkedin"
  },
  {
    "text": "Reddit",
    "url": "https://9to5mac.com/2022/07/29/app-store-ads-expanding/?share=reddit"
  },
  {
    "text": "expand full story ",
    "url": "https://9to5mac.com/2022/07/29/app-store-ads-expanding/#more-824135"
  },
  {
    "text": "HomeKit Weekly: Eve Cam can double as an outdoor camera through a window thanks to flexible mounting options",
    "url": "https://9to5mac.com/2022/07/29/eve-cam-2/"
  },
  {
    "text": "\n\t\t\t\t\t\t\t\tBradley Chambers\n\t\t\t\t\t\t\t",
    "url": "https://9to5mac.com/author/bradleychambers/"
  },
  {
    "text": "@bradleychambers",
    "url": "https://twitter.com/intent/follow?screen_name=bradleychambers&original_referer=https%3A%2F%2F9to5mac.com"
  },
  {
    "text": "HomeKit",
    "url": "https://9to5mac.com/guides/homekit/"
  },
  {
    "text": "HomeKit Weekly",
    "url": "https://9to5mac.com/guides/homekit-weekly/"
  },
  {
    "text": "\n\t\t\t\t\t\t\t\t\n\t\t\t\t\t\t\t",
    "url": "https://9to5mac.com/2022/07/29/eve-cam-2/"
  },
  {
    "text": "3 Comments",
    "url": "https://9to5mac.com/2022/07/29/eve-cam-2/#disqus_thread"
  },
  {
    "text": "Facebook",
    "url": "https://9to5mac.com/2022/07/29/eve-cam-2/?share=facebook"
  },
  {
    "text": "Twitter",
    "url": "https://9to5mac.com/2022/07/29/eve-cam-2/?share=twitter"
  },
  {
    "text": "Pinterest",
    "url": "https://9to5mac.com/2022/07/29/eve-cam-2/?share=pinterest"
  },
  {
    "text": "LinkedIn",
    "url": "https://9to5mac.com/2022/07/29/eve-cam-2/?share=linkedin"
  },
  {
    "text": "Reddit",
    "url": "https://9to5mac.com/2022/07/29/eve-cam-2/?share=reddit"
  },
  {
    "text": "temporary living situation",
    "url": "https://9to5mac.com/2022/06/24/eufycam-pro/"
  },
  {
    "text": "Eve Cam",
    "url": "https://amzn.to/3aaUBo6"
  },
  {
    "text": "expand full story ",
    "url": "https://9to5mac.com/2022/07/29/eve-cam-2/#more-817780"
  },
  {
    "text": "9to5Toys\u00a0",
    "url": "https://9to5toys.com/"
  },
  {
    "text": "",
    "url": "http://www.facebook.com/pages/9to5toyscom/228249133858390"
  },
  {
    "text": "",
    "url": "https://twitter.com/9to5toys"
  },
  {
    "text": "",
    "url": "https://www.youtube.com/9to5toys?sub_confirmation=1"
  },
  {
    "text": "\n\t\t\t\t\t\t\t\t\t\n\t\t\t\t\t\t\t\t\t\t\n\t\t\t\t\t\t\t\t\t\n\t\t\t\t\t\t\t\t",
    "url": "https://itunes.apple.com/us/podcast/9to5toys-daily-9to5toys/id1404999371"
  },
  {
    "text": "\n\t\t\t\t\t\t\t\t\t\n\t\t\t\t\t\t\t\t\t\t\n\t\t\t\t\t\t\t\t\t\n\t\t\t\t\t\t\t\t",
    "url": "https://9to5toys.com/9to5toys-newsletter-signup/"
  },
  {
    "text": "\n\t\t\t\t\t\t\t\t\n\t\t\t\t\t\t\t\tViewSonic\u2019s ELITE 32-inch 4K 150Hz Gaming Monitor falls to new low of $860, more from $544\n\t\t\t\t\t\t\t",
    "url": "https://9to5toys.com/2022/07/29/viewsonics-elite-32-inch-4k-150hz-gaming-monitor-falls-to-new-low-of-860-more-from-544/"
  },
  {
    "text": "\n\t\t\t\t\t\t\t\t\n\t\t\t\t\t\t\t\tSave $26 on Dreo\u2019s Macro Pro Air Purifier with HEPA filtration at the low price of $114\n\t\t\t\t\t\t\t",
    "url": "https://9to5toys.com/2022/07/29/save-26-on-dreos-macro-pro-air-purifier-with-hepa-filtration-at-the-low-price-of-114/"
  },
  {
    "text": "\n\t\t\t\t\t\t\t\t\n\t\t\t\t\t\t\t\tDatacolor\u2019s SpyderX Elite Color Control Kit will calibrate your monitor and pictures for\u2026\n\t\t\t\t\t\t\t",
    "url": "https://9to5toys.com/2022/07/29/datacolors-spyderx-elite-color-control-kit-will-calibrate-your-monitor-and-pictures-for-190/"
  },
  {
    "text": "\n\t\t\t\t\t\t\t\t\n\t\t\t\t\t\t\t\tTwelve South\u2019s PowerPic mod wireless charger returns to all-time low at $48 (20% off)\n\t\t\t\t\t\t\t",
    "url": "https://9to5toys.com/2022/07/29/twelve-south-powerpic-mod-sale-amazon/"
  },
  {
    "text": "\n\t\t\t\t\t\t\t\t\n\t\t\t\t\t\t\t\tPARIS RH\u00d4NE Food Dehydrator falls to new all-time low at Amazon, now $99 (Reg. $170)\n\t\t\t\t\t\t\t",
    "url": "https://9to5toys.com/2022/07/29/paris-rhone-food-dehydrator/"
  },
  {
    "text": "\n\t\t\t\t\t\t\t\t\t",
    "url": "https://9to5mac.com/2022/07/29/how-to-watch-ufc-277-pena-vs-nunes/"
  },
  {
    "text": "\n\t\t\t\t\t\t\t\t\t\tHow to watch UFC 277 Pe\u00f1a vs Nunes on iPhone, Apple TV, web\n\t\t\t\t\t\t\t\t\t",
    "url": "https://9to5mac.com/2022/07/29/how-to-watch-ufc-277-pena-vs-nunes/"
  },
  {
    "text": "\n\t\t\t\t\t\t\t\t\t\t\tMichael Potuck\n\t\t\t\t\t\t\t\t\t\t",
    "url": "https://9to5mac.com/author/michaelpotuck/"
  },
  {
    "text": "\n\t\t\t\t\t\t\t\t\t\n\t\t\t\t\t\t\t\t\t\t\n\t\t\t\t\t\t\t\t\t\n\t\t\t\t\t\t\t\t",
    "url": "https://9to5mac.com/2022/07/29/how-to-watch-ufc-277-pena-vs-nunes/"
  },
  {
    "text": "9to5Mac Daily: July 29, 2022 \u2013\u00a0Apple earnings, Instagram changes",
    "url": "https://9to5mac.com/2022/07/29/9to5mac-daily-july-29-2022-apple-earnings-instagram-changes/"
  },
  {
    "text": "\n\t\t\t\t\t\t\t\tSeth Kurkowski\n\t\t\t\t\t\t\t",
    "url": "https://9to5mac.com/author/sethkurk/"
  },
  {
    "text": "@SethKurk",
    "url": "https://twitter.com/intent/follow?screen_name=SethKurk&original_referer=https%3A%2F%2F9to5mac.com"
  },
  {
    "text": "9to5Mac Podcast Network",
    "url": "https://9to5mac.com/guides/podcast/"
  },
  {
    "text": "9to5Mac Daily Podcast",
    "url": "https://9to5mac.com/guides/9to5mac-daily/"
  },
  {
    "text": "\n\t\t\t\t\t\t\t\t\n\t\t\t\t\t\t\t",
    "url": "https://9to5mac.com/2022/07/29/9to5mac-daily-july-29-2022-apple-earnings-instagram-changes/"
  },
  {
    "text": "Add Your Comment",
    "url": "https://9to5mac.com/2022/07/29/9to5mac-daily-july-29-2022-apple-earnings-instagram-changes/#disqus_thread"
  },
  {
    "text": "Facebook",
    "url": "https://9to5mac.com/2022/07/29/9to5mac-daily-july-29-2022-apple-earnings-instagram-changes/?share=facebook"
  },
  {
    "text": "Twitter",
    "url": "https://9to5mac.com/2022/07/29/9to5mac-daily-july-29-2022-apple-earnings-instagram-changes/?share=twitter"
  },
  {
    "text": "Pinterest",
    "url": "https://9to5mac.com/2022/07/29/9to5mac-daily-july-29-2022-apple-earnings-instagram-changes/?share=pinterest"
  },
  {
    "text": "LinkedIn",
    "url": "https://9to5mac.com/2022/07/29/9to5mac-daily-july-29-2022-apple-earnings-instagram-changes/?share=linkedin"
  },
  {
    "text": "Reddit",
    "url": "https://9to5mac.com/2022/07/29/9to5mac-daily-july-29-2022-apple-earnings-instagram-changes/?share=reddit"
  },
  {
    "text": "on iTunes and Apple\u2019s Podcasts app",
    "url": "https://podcasts.apple.com/us/podcast/9to5mac-daily/id1331816080"
  },
  {
    "text": "Stitcher",
    "url": "https://www.stitcher.com/podcast/9to5mac-daily"
  },
  {
    "text": "TuneIn",
    "url": "https://tunein.com/radio/9to5Mac-Daily-p1089524/"
  },
  {
    "text": "Google Play",
    "url": "https://play.google.com/music/m/I5d4dzs7dauazmfxvvrynyiuram?t=9to5Mac_Daily"
  },
  {
    "text": "dedicated RSS feed",
    "url": "https://feedpress.me/9to5macdaily"
  },
  {
    "text": "Sponsored by Kolide",
    "url": "https://l.kolide.co/3udxgJg"
  },
  {
    "text": "Learn more here",
    "url": "https://l.kolide.co/3udxgJg"
  },
  {
    "text": "expand full story ",
    "url": "https://9to5mac.com/2022/07/29/9to5mac-daily-july-29-2022-apple-earnings-instagram-changes/#more-824105"
  },
  {
    "text": "iPad chip list: Here\u2019s what Apple Silicon is in every model",
    "url": "https://9to5mac.com/2022/07/29/ipad-chip-list/"
  },
  {
    "text": "\n\t\t\t\t\t\t\t\tMichael Potuck\n\t\t\t\t\t\t\t",
    "url": "https://9to5mac.com/author/michaelpotuck/"
  },
  {
    "text": "@michaelpotuck",
    "url": "https://twitter.com/intent/follow?screen_name=michaelpotuck&original_referer=https%3A%2F%2F9to5mac.com"
  },
  {
    "text": "iPad",
    "url": "https://9to5mac.com/guides/ipad/"
  },
  {
    "text": "How-to",
    "url": "https://9to5mac.com/guides/how-to/"
  },
  {
    "text": "\n\t\t\t\t\t\t\t\t\n\t\t\t\t\t\t\t",
    "url": "https://9to5mac.com/2022/07/29/ipad-chip-list/"
  },
  {
    "text": "1 Comment",
    "url": "https://9to5mac.com/2022/07/29/ipad-chip-list/#disqus_thread"
  },
  {
    "text": "Facebook",
    "url": "https://9to5mac.com/2022/07/29/ipad-chip-list/?share=facebook"
  },
  {
    "text": "Twitter",
    "url": "https://9to5mac.com/2022/07/29/ipad-chip-list/?share=twitter"
  },
  {
    "text": "Pinterest",
    "url": "https://9to5mac.com/2022/07/29/ipad-chip-list/?share=pinterest"
  },
  {
    "text": "LinkedIn",
    "url": "https://9to5mac.com/2022/07/29/ipad-chip-list/?share=linkedin"
  },
  {
    "text": "Reddit",
    "url": "https://9to5mac.com/2022/07/29/ipad-chip-list/?share=reddit"
  },
  {
    "text": "expand full story ",
    "url": "https://9to5mac.com/2022/07/29/ipad-chip-list/#more-824209"
  },
  {
    "text": "DroneDJ\u00a0",
    "url": "https://dronedj.com"
  },
  {
    "text": "",
    "url": "https://www.facebook.com/dronedj"
  },
  {
    "text": "",
    "url": "https://twitter.com/dronedj"
  },
  {
    "text": "",
    "url": "https://www.youtube.com/c/dronedj?sub_confirmation=1"
  },
  {
    "text": "\n\t\t\t\t\t\t\t\t\t\n\t\t\t\t\t\t\t\t\t\t\n\t\t\t\t\t\t\t\t\t\n\t\t\t\t\t\t\t\t",
    "url": "http://9to5mac.us9.list-manage.com/subscribe?u=53ec2d4dd6eb242346cdddfa2&id=ce73234260"
  },
  {
    "text": "\n\t\t\t\t\t\t\t\t\n\t\t\t\t\t\t\t\tFAA\u2019s Remote ID rule for drones is constitutional, DC court rules\n\t\t\t\t\t\t\t",
    "url": "https://dronedj.com/2022/07/29/faa-remote-id-drone-rule/"
  },
  {
    "text": "\n\t\t\t\t\t\t\t\t\n\t\t\t\t\t\t\t\t6 reasons why DJI agricultural drone sales are skyrocketing\n\t\t\t\t\t\t\t",
    "url": "https://dronedj.com/2022/07/29/dji-agricultural-drone-sales/"
  },
  {
    "text": "\n\t\t\t\t\t\t\t\t\n\t\t\t\t\t\t\t\tEyeing looming drone and AAM services, UK reviews aviation laws\n\t\t\t\t\t\t\t",
    "url": "https://dronedj.com/2022/07/29/uk-law-drones-aam/"
  },
  {
    "text": "\n\t\t\t\t\t\t\t\t\n\t\t\t\t\t\t\t\tDJI updates Terra mapping software with major improvements\n\t\t\t\t\t\t\t",
    "url": "https://dronedj.com/2022/07/29/dji-terra-software/"
  },
  {
    "text": "\n\t\t\t\t\t\t\t\t\n\t\t\t\t\t\t\t\tSony updates Airpeak Flight drone app with useful new features\n\t\t\t\t\t\t\t",
    "url": "https://dronedj.com/2022/07/29/sony-airpeak-drone-flight-app/"
  },
  {
    "text": "\n\t\t\t\t\t\t\t\t\t",
    "url": "https://9to5mac.com/2022/07/29/m1-pro-macbook-pro-m2-sale-more/"
  },
  {
    "text": "\n\t\t\t\t\t\t\t\t\t\tAll-time lows on M1 Pro MacBook Pros, M2 MacBook Pro, more in weekend\u2019s best deals\n\t\t\t\t\t\t\t\t\t",
    "url": "https://9to5mac.com/2022/07/29/m1-pro-macbook-pro-m2-sale-more/"
  },
  {
    "text": "\n\t\t\t\t\t\t\t\t\t\t\tRikka Altland\n\t\t\t\t\t\t\t\t\t\t",
    "url": "https://9to5mac.com/author/blairaltland/"
  },
  {
    "text": "16- and 14-inch M1 Pro MacBook Pros ",
    "url": "https://9to5toys.com/2022/07/29/m1-pro-macbook-pro-amazon-discount/"
  },
  {
    "text": "at $1,699",
    "url": "https://9to5toys.com/2022/07/29/m1-pro-macbook-pro-amazon-discount/"
  },
  {
    "text": "M2 MacBook Pro",
    "url": "https://9to5toys.com/2022/07/28/m2-macbook-pro-discount/"
  },
  {
    "text": "a $1,049 price tag",
    "url": "https://9to5toys.com/2022/07/28/m2-macbook-pro-discount/"
  },
  {
    "text": "12.9-inch iPad Pro deal",
    "url": "https://9to5toys.com/2022/07/29/apples-prev-gen-12-9-inch-ipad-pro-is-an-even-better-value-at-700-refurb-save-299/"
  },
  {
    "text": "at $700",
    "url": "https://9to5toys.com/2022/07/29/apples-prev-gen-12-9-inch-ipad-pro-is-an-even-better-value-at-700-refurb-save-299/"
  },
  {
    "text": "\n\t\t\t\t\t\t\t\t\t\n\t\t\t\t\t\t\t\t\t\t\n\t\t\t\t\t\t\t\t\t\n\t\t\t\t\t\t\t\t",
    "url": "https://9to5mac.com/2022/07/29/m1-pro-macbook-pro-m2-sale-more/"
  },
  {
    "text": "\n\t\t\t\t\t\t\t\t\t",
    "url": "https://9to5google.com/2022/07/29/amazon-drive-shutting-down/"
  },
  {
    "text": "\n\t\t\t\t\t\t\t\t\t\tAmazon Drive is shutting down in 2023, no impact to Amazon Photos\n\t\t\t\t\t\t\t\t\t",
    "url": "https://9to5google.com/2022/07/29/amazon-drive-shutting-down/"
  },
  {
    "text": "\n\t\t\t\t\t\t\t\t\t\t\t9to5Google\n\t\t\t\t\t\t\t\t\t\t",
    "url": "https://9to5google.com"
  },
  {
    "text": "\n\t\t\t\t\t\t\t\t\t\n\t\t\t\t\t\t\t\t\t\t\n\t\t\t\t\t\t\t\t\t\n\t\t\t\t\t\t\t\t",
    "url": "https://9to5google.com/2022/07/29/amazon-drive-shutting-down/"
  },
  {
    "text": "Satechi Aluminum Desktop Stand Review \u2013 a sturdy tool to prop up your iPad",
    "url": "https://9to5mac.com/2022/07/29/ipad-stand-satechi/"
  },
  {
    "text": "\n\t\t\t\t\t\t\t\tAllison McDaniel\n\t\t\t\t\t\t\t",
    "url": "https://9to5mac.com/author/allisonmcdaniel/"
  },
  {
    "text": "@aamcdani",
    "url": "https://twitter.com/intent/follow?screen_name=aamcdani&original_referer=https%3A%2F%2F9to5mac.com"
  },
  {
    "text": "iPad",
    "url": "https://9to5mac.com/guides/ipad/"
  },
  {
    "text": "Reviews",
    "url": "https://9to5mac.com/guides/review/"
  },
  {
    "text": "Satechi",
    "url": "https://9to5mac.com/guides/satechi/"
  },
  {
    "text": "\n\t\t\t\t\t\t\t\t\n\t\t\t\t\t\t\t",
    "url": "https://9to5mac.com/2022/07/29/ipad-stand-satechi/"
  },
  {
    "text": "Add Your Comment",
    "url": "https://9to5mac.com/2022/07/29/ipad-stand-satechi/#disqus_thread"
  },
  {
    "text": "Facebook",
    "url": "https://9to5mac.com/2022/07/29/ipad-stand-satechi/?share=facebook"
  },
  {
    "text": "Twitter",
    "url": "https://9to5mac.com/2022/07/29/ipad-stand-satechi/?share=twitter"
  },
  {
    "text": "Pinterest",
    "url": "https://9to5mac.com/2022/07/29/ipad-stand-satechi/?share=pinterest"
  },
  {
    "text": "LinkedIn",
    "url": "https://9to5mac.com/2022/07/29/ipad-stand-satechi/?share=linkedin"
  },
  {
    "text": "Reddit",
    "url": "https://9to5mac.com/2022/07/29/ipad-stand-satechi/?share=reddit"
  },
  {
    "text": "expand full story ",
    "url": "https://9to5mac.com/2022/07/29/ipad-stand-satechi/#more-822682"
  },
  {
    "text": "9to5Google\u00a0",
    "url": "https://9to5google.com/"
  },
  {
    "text": "",
    "url": "http://www.facebook.com/pages/9to5Google/218132111544562"
  },
  {
    "text": "",
    "url": "http://twitter.com/9to5google"
  },
  {
    "text": "",
    "url": "https://www.youtube.com/c/9to5google?sub_confirmation=1"
  },
  {
    "text": "\n\t\t\t\t\t\t\t\t\t\n\t\t\t\t\t\t\t\t\t\t\n\t\t\t\t\t\t\t\t\t\n\t\t\t\t\t\t\t\t",
    "url": "https://itunes.apple.com/us/podcast/alphabet-scoop/id1359922601?mt=2"
  },
  {
    "text": "\n\t\t\t\t\t\t\t\t\t\n\t\t\t\t\t\t\t\t\t\t\n\t\t\t\t\t\t\t\t\t\n\t\t\t\t\t\t\t\t",
    "url": "https://eepurl.com/bdw6AH"
  },
  {
    "text": "\n\t\t\t\t\t\t\t\t\n\t\t\t\t\t\t\t\tNearly two years later, Chromecast with Google TV still cannot use Nest Audio as speakers\n\t\t\t\t\t\t\t",
    "url": "https://9to5google.com/2022/07/29/chromecast-google-tv-nest-audio-speakers/"
  },
  {
    "text": "\n\t\t\t\t\t\t\t\t\n\t\t\t\t\t\t\t\tBandwidth: Multiversus on Boosteroid, Amazon Luna goes without Luna+ addition this month\n\t\t\t\t\t\t\t",
    "url": "https://9to5google.com/2022/07/29/bandwidth-multiversus-on-boosteroid/"
  },
  {
    "text": "\n\t\t\t\t\t\t\t\t\n\t\t\t\t\t\t\t\tStadia Changelog: Two new games arrive along with a bid for the future\n\t\t\t\t\t\t\t",
    "url": "https://9to5google.com/2022/07/29/stadia-neighbours-from-hell/"
  },
  {
    "text": "\n\t\t\t\t\t\t\t\t\n\t\t\t\t\t\t\t\tHere are the other colors Google considered for Pixel Buds Pro\n\t\t\t\t\t\t\t",
    "url": "https://9to5google.com/2022/07/29/pixel-buds-pro-colors/"
  },
  {
    "text": "\n\t\t\t\t\t\t\t\t\n\t\t\t\t\t\t\t\tAndroid app deals of the day: Doom & Destiny Worlds, Majesty, Table Top Racing, and more\n\t\t\t\t\t\t\t",
    "url": "https://9to5toys.com/2022/07/29/android-app-deals-doom-destiny-3/"
  },
  {
    "text": "Apple union-busting was \u2018traumatic,\u2019 say workers \u2013 even included immigration assistance threat",
    "url": "https://9to5mac.com/2022/07/29/apple-union-busting-2/"
  },
  {
    "text": "\n\t\t\t\t\t\t\t\tBen Lovejoy\n\t\t\t\t\t\t\t",
    "url": "https://9to5mac.com/author/benlovejoy/"
  },
  {
    "text": "@benlovejoy",
    "url": "https://twitter.com/intent/follow?screen_name=benlovejoy&original_referer=https%3A%2F%2F9to5mac.com"
  },
  {
    "text": "AAPL Company",
    "url": "https://9to5mac.com/guides/aapl/"
  },
  {
    "text": "Apple Retail",
    "url": "https://9to5mac.com/guides/apple-store/"
  },
  {
    "text": "Unionization",
    "url": "https://9to5mac.com/guides/unionization/"
  },
  {
    "text": "\n\t\t\t\t\t\t\t\t\n\t\t\t\t\t\t\t",
    "url": "https://9to5mac.com/2022/07/29/apple-union-busting-2/"
  },
  {
    "text": "38 Comments",
    "url": "https://9to5mac.com/2022/07/29/apple-union-busting-2/#disqus_thread"
  },
  {
    "text": "Facebook",
    "url": "https://9to5mac.com/2022/07/29/apple-union-busting-2/?share=facebook"
  },
  {
    "text": "Twitter",
    "url": "https://9to5mac.com/2022/07/29/apple-union-busting-2/?share=twitter"
  },
  {
    "text": "Pinterest",
    "url": "https://9to5mac.com/2022/07/29/apple-union-busting-2/?share=pinterest"
  },
  {
    "text": "LinkedIn",
    "url": "https://9to5mac.com/2022/07/29/apple-union-busting-2/?share=linkedin"
  },
  {
    "text": "Reddit",
    "url": "https://9to5mac.com/2022/07/29/apple-union-busting-2/?share=reddit"
  },
  {
    "text": "union",
    "url": "https://9to5mac.com/guides/unionization/"
  },
  {
    "text": "the first Apple Store to unionize",
    "url": "https://9to5mac.com/2022/06/18/apple-store-union-marylan/"
  },
  {
    "text": "Apple",
    "url": "https://9to5mac.com/guides/aapl/"
  },
  {
    "text": "expand full story ",
    "url": "https://9to5mac.com/2022/07/29/apple-union-busting-2/#more-824040"
  },
  {
    "text": "\n\t\t\t\t\t\t\t\t\t",
    "url": "https://9to5mac.com/2022/07/29/apple-arcade-games/"
  },
  {
    "text": "\n\t\t\t\t\t\t\t\t\t\tApple Arcade games for iPhone, Mac, Apple TV [New: Kingdom Rush Vengeance TD+]\n\t\t\t\t\t\t\t\t\t",
    "url": "https://9to5mac.com/2022/07/29/apple-arcade-games/"
  },
  {
    "text": "\n\t\t\t\t\t\t\t\t\t\t\tMichael Potuck\n\t\t\t\t\t\t\t\t\t\t",
    "url": "https://9to5mac.com/author/michaelpotuck/"
  },
  {
    "text": "Apple Arcade",
    "url": "https://9to5mac.com/guides/apple-arcade/"
  },
  {
    "text": "over 200 games",
    "url": "https://9to5mac.com/2021/08/06/apple-arcade-hits-200-games-with-original-and-classic-titles-in-its-catalog/"
  },
  {
    "text": "\n\t\t\t\t\t\t\t\t\t\n\t\t\t\t\t\t\t\t\t\t\n\t\t\t\t\t\t\t\t\t\n\t\t\t\t\t\t\t\t",
    "url": "https://9to5mac.com/2022/07/29/apple-arcade-games/"
  },
  {
    "text": "Apple Brompton Road store opening: A 360-degree video tour",
    "url": "https://9to5mac.com/2022/07/29/apple-brompton-road-3/"
  },
  {
    "text": "\n\t\t\t\t\t\t\t\tBen Lovejoy\n\t\t\t\t\t\t\t",
    "url": "https://9to5mac.com/author/benlovejoy/"
  },
  {
    "text": "@benlovejoy",
    "url": "https://twitter.com/intent/follow?screen_name=benlovejoy&original_referer=https%3A%2F%2F9to5mac.com"
  },
  {
    "text": "Apple Retail",
    "url": "https://9to5mac.com/guides/apple-store/"
  },
  {
    "text": "\n\t\t\t\t\t\t\t\t\n\t\t\t\t\t\t\t",
    "url": "https://9to5mac.com/2022/07/29/apple-brompton-road-3/"
  },
  {
    "text": "3 Comments",
    "url": "https://9to5mac.com/2022/07/29/apple-brompton-road-3/#disqus_thread"
  },
  {
    "text": "Facebook",
    "url": "https://9to5mac.com/2022/07/29/apple-brompton-road-3/?share=facebook"
  },
  {
    "text": "Twitter",
    "url": "https://9to5mac.com/2022/07/29/apple-brompton-road-3/?share=twitter"
  },
  {
    "text": "Pinterest",
    "url": "https://9to5mac.com/2022/07/29/apple-brompton-road-3/?share=pinterest"
  },
  {
    "text": "LinkedIn",
    "url": "https://9to5mac.com/2022/07/29/apple-brompton-road-3/?share=linkedin"
  },
  {
    "text": "Reddit",
    "url": "https://9to5mac.com/2022/07/29/apple-brompton-road-3/?share=reddit"
  },
  {
    "text": "Apple Brompton Road store",
    "url": "https://9to5mac.com/2022/07/26/apple-brompton-road-2/"
  },
  {
    "text": "third flagship Apple Store",
    "url": "https://9to5mac.com/2022/07/18/apple-brompton-road/"
  },
  {
    "text": "expand full story ",
    "url": "https://9to5mac.com/2022/07/29/apple-brompton-road-3/#more-823852"
  },
  {
    "text": "Best Apple deals from 9to5Toys\u00a0",
    "url": "https://9to5toys.com/guides/apple/"
  },
  {
    "text": "",
    "url": "http://www.facebook.com/pages/9to5toyscom/228249133858390"
  },
  {
    "text": "",
    "url": "https://twitter.com/9to5toys"
  },
  {
    "text": "",
    "url": "https://www.youtube.com/9to5toys?sub_confirmation=1"
  },
  {
    "text": "\n\t\t\t\t\t\t\t\t\t\n\t\t\t\t\t\t\t\t\t\t\n\t\t\t\t\t\t\t\t\t\n\t\t\t\t\t\t\t\t",
    "url": "https://itunes.apple.com/us/podcast/9to5toys-daily-9to5toys/id1404999371"
  },
  {
    "text": "\n\t\t\t\t\t\t\t\t\t\n\t\t\t\t\t\t\t\t\t\t\n\t\t\t\t\t\t\t\t\t\n\t\t\t\t\t\t\t\t",
    "url": "https://9to5toys.com/9to5toys-newsletter-signup/"
  },
  {
    "text": "\n\t\t\t\t\t\t\t\t\n\t\t\t\t\t\t\t\tApple\u2019s prev-gen 12.9-inch iPad Pro is an even better value at $700 (Refurb, Save $299+)\n\t\t\t\t\t\t\t",
    "url": "https://9to5toys.com/2022/07/29/apples-prev-gen-12-9-inch-ipad-pro-is-an-even-better-value-at-700-refurb-save-299/"
  },
  {
    "text": "\n\t\t\t\t\t\t\t\t\n\t\t\t\t\t\t\t\tApple 16- and 14-inch M1 Pro MacBook Pros hit all-time lows from $1,699 (Save $300+)\n\t\t\t\t\t\t\t",
    "url": "https://9to5toys.com/2022/07/29/m1-pro-macbook-pro-amazon-discount/"
  },
  {
    "text": "\n\t\t\t\t\t\t\t\t\n\t\t\t\t\t\t\t\tM2 MacBook Pro falls to new all-time low from $1,049 following $250 discount\n\t\t\t\t\t\t\t",
    "url": "https://9to5toys.com/2022/07/28/m2-macbook-pro-discount/"
  },
  {
    "text": "\n\t\t\t\t\t\t\t\t\n\t\t\t\t\t\t\t\tNew all-time low brings Apple\u2019s M1 Max Mac Studio down to $1,849 (Save $150)\n\t\t\t\t\t\t\t",
    "url": "https://9to5toys.com/2022/07/27/mac-studio-expercom-summer-sale/"
  },
  {
    "text": "\n\t\t\t\t\t\t\t\t\n\t\t\t\t\t\t\t\tApple launches largest $5 movie sale of the year with action flicks, dramas, much more\n\t\t\t\t\t\t\t",
    "url": "https://9to5toys.com/2022/07/26/apple-5-dollar-itunes-movie-sale/"
  },
  {
    "text": "Apple Q3 2022 results show iPhone (just barely) creating a new record",
    "url": "https://9to5mac.com/2022/07/29/apple-q3-2022/"
  },
  {
    "text": "\n\t\t\t\t\t\t\t\tBen Lovejoy\n\t\t\t\t\t\t\t",
    "url": "https://9to5mac.com/author/benlovejoy/"
  },
  {
    "text": "@benlovejoy",
    "url": "https://twitter.com/intent/follow?screen_name=benlovejoy&original_referer=https%3A%2F%2F9to5mac.com"
  },
  {
    "text": "AAPL Company",
    "url": "https://9to5mac.com/guides/aapl/"
  },
  {
    "text": "\n\t\t\t\t\t\t\t\t\n\t\t\t\t\t\t\t",
    "url": "https://9to5mac.com/2022/07/29/apple-q3-2022/"
  },
  {
    "text": "3 Comments",
    "url": "https://9to5mac.com/2022/07/29/apple-q3-2022/#disqus_thread"
  },
  {
    "text": "Facebook",
    "url": "https://9to5mac.com/2022/07/29/apple-q3-2022/?share=facebook"
  },
  {
    "text": "Twitter",
    "url": "https://9to5mac.com/2022/07/29/apple-q3-2022/?share=twitter"
  },
  {
    "text": "Pinterest",
    "url": "https://9to5mac.com/2022/07/29/apple-q3-2022/?share=pinterest"
  },
  {
    "text": "LinkedIn",
    "url": "https://9to5mac.com/2022/07/29/apple-q3-2022/?share=linkedin"
  },
  {
    "text": "Reddit",
    "url": "https://9to5mac.com/2022/07/29/apple-q3-2022/?share=reddit"
  },
  {
    "text": "the announcement of Apple Q3 2022 earnings",
    "url": "https://9to5mac.com/2022/07/28/apple-q3-2022-earnings/"
  },
  {
    "text": "the analysts were right",
    "url": "https://9to5mac.com/2022/07/27/aapl-earnings-q3-2022/"
  },
  {
    "text": "expand full story ",
    "url": "https://9to5mac.com/2022/07/29/apple-q3-2022/#more-824009"
  },
  {
    "text": "\n\t\t\t\t\t\t\t\t\t",
    "url": "https://9to5mac.com/2022/07/29/apple-tv-plus-tv-shows-movies-guide/"
  },
  {
    "text": "\n\t\t\t\t\t\t\t\t\t\tApple TV+ Guide: Every Apple TV show and movie available now\n\t\t\t\t\t\t\t\t\t",
    "url": "https://9to5mac.com/2022/07/29/apple-tv-plus-tv-shows-movies-guide/"
  },
  {
    "text": "\n\t\t\t\t\t\t\t\t\t\t\tBenjamin Mayo\n\t\t\t\t\t\t\t\t\t\t",
    "url": "https://9to5mac.com/author/benjaminmayo/"
  },
  {
    "text": "Apple TV+",
    "url": "https://tinyurl.com/getappletvplus"
  },
  {
    "text": "\n\t\t\t\t\t\t\t\t\t\n\t\t\t\t\t\t\t\t\t\t\n\t\t\t\t\t\t\t\t\t\n\t\t\t\t\t\t\t\t",
    "url": "https://9to5mac.com/2022/07/29/apple-tv-plus-tv-shows-movies-guide/"
  },
  {
    "text": "Apple now selling iPhone 12 mini in its US Refurbished Store for the first time",
    "url": "https://9to5mac.com/2022/07/28/apple-selling-iphone-12-mini-refurbished/"
  },
  {
    "text": "\n\t\t\t\t\t\t\t\tFilipe Esp\u00f3sito\n\t\t\t\t\t\t\t",
    "url": "https://9to5mac.com/author/filipeesposito/"
  },
  {
    "text": "@filipeesposito",
    "url": "https://twitter.com/intent/follow?screen_name=filipeesposito&original_referer=https%3A%2F%2F9to5mac.com"
  },
  {
    "text": "Refurbished",
    "url": "https://9to5mac.com/guides/refurbished/"
  },
  {
    "text": "iPhone 12 mini",
    "url": "https://9to5mac.com/guides/iphone-12-mini/"
  },
  {
    "text": "\n\t\t\t\t\t\t\t\t\n\t\t\t\t\t\t\t",
    "url": "https://9to5mac.com/2022/07/28/apple-selling-iphone-12-mini-refurbished/"
  },
  {
    "text": "7 Comments",
    "url": "https://9to5mac.com/2022/07/28/apple-selling-iphone-12-mini-refurbished/#disqus_thread"
  },
  {
    "text": "Facebook",
    "url": "https://9to5mac.com/2022/07/28/apple-selling-iphone-12-mini-refurbished/?share=facebook"
  },
  {
    "text": "Twitter",
    "url": "https://9to5mac.com/2022/07/28/apple-selling-iphone-12-mini-refurbished/?share=twitter"
  },
  {
    "text": "Pinterest",
    "url": "https://9to5mac.com/2022/07/28/apple-selling-iphone-12-mini-refurbished/?share=pinterest"
  },
  {
    "text": "LinkedIn",
    "url": "https://9to5mac.com/2022/07/28/apple-selling-iphone-12-mini-refurbished/?share=linkedin"
  },
  {
    "text": "Reddit",
    "url": "https://9to5mac.com/2022/07/28/apple-selling-iphone-12-mini-refurbished/?share=reddit"
  },
  {
    "text": "expand full story ",
    "url": "https://9to5mac.com/2022/07/28/apple-selling-iphone-12-mini-refurbished/#more-823992"
  },
  {
    "text": "Electrek\u00a0",
    "url": "https://electrek.co"
  },
  {
    "text": "",
    "url": "https://www.facebook.com/electrekco"
  },
  {
    "text": "",
    "url": "http://twitter.com/electrekco"
  },
  {
    "text": "",
    "url": "https://www.youtube.com/c/electrekco?sub_confirmation=1"
  },
  {
    "text": "\n\t\t\t\t\t\t\t\t\t\n\t\t\t\t\t\t\t\t\t\t\n\t\t\t\t\t\t\t\t\t\n\t\t\t\t\t\t\t\t",
    "url": "https://itunes.apple.com/us/podcast/electrek/id1320055779"
  },
  {
    "text": "\n\t\t\t\t\t\t\t\t\t\n\t\t\t\t\t\t\t\t\t\t\n\t\t\t\t\t\t\t\t\t\n\t\t\t\t\t\t\t\t",
    "url": "https://eepurl.com/bTzCKT"
  },
  {
    "text": "\n\t\t\t\t\t\t\t\t\n\t\t\t\t\t\t\t\t2023 Chevy Bolt EV is still the best value EV in America, by far\n\t\t\t\t\t\t\t",
    "url": "https://electrek.co/2022/07/29/2023-chevy-bolt-ev/"
  },
  {
    "text": "\n\t\t\t\t\t\t\t\t\n\t\t\t\t\t\t\t\tPodcast: Tesla Supercharger Cube lounge, new EV federal credit, Mercedes-Benz EQXX, and more\n\t\t\t\t\t\t\t",
    "url": "https://electrek.co/2022/07/29/podcast-tesla-supercharger-cube-lounge-new-ev-federal-credit-mercedes-benz-eqxx/"
  },
  {
    "text": "\n\t\t\t\t\t\t\t\t\n\t\t\t\t\t\t\t\tThis company is buying 200 Tesla vehicles per week and is now ordering 23,000 EVs\n\t\t\t\t\t\t\t",
    "url": "https://electrek.co/2022/07/29/autonomy-buying-200-tesla-vehicles-per-week-ordering-23000-evs/"
  },
  {
    "text": "\n\t\t\t\t\t\t\t\t\n\t\t\t\t\t\t\t\tBLACK+DECKER blower/vacuum/mulcher cleans your yard ahead of fall at $67 in New Green Deals\n\t\t\t\t\t\t\t",
    "url": "https://electrek.co/2022/07/29/black-decker-blower-vacuum-combo-more-new-green-deals/"
  },
  {
    "text": "\n\t\t\t\t\t\t\t\t\n\t\t\t\t\t\t\t\tElectric trucks like Tesla Semi will get up to $40,000 in incentives with new bill\n\t\t\t\t\t\t\t",
    "url": "https://electrek.co/2022/07/29/electric-trucks-tesla-semi-40000-incentives-new-bill/"
  },
  {
    "text": "\n\t\t\t\t\t\t\t\t\t",
    "url": "https://9to5mac.com/2022/07/28/how-to-watch-surface-tv-show/"
  },
  {
    "text": "\n\t\t\t\t\t\t\t\t\t\tHow to watch Surface TV show on Apple TV+\n\t\t\t\t\t\t\t\t\t",
    "url": "https://9to5mac.com/2022/07/28/how-to-watch-surface-tv-show/"
  },
  {
    "text": "\n\t\t\t\t\t\t\t\t\t\t\tBenjamin Mayo\n\t\t\t\t\t\t\t\t\t\t",
    "url": "https://9to5mac.com/author/benjaminmayo/"
  },
  {
    "text": "Apple TV+",
    "url": "https://tinyurl.com/getappletvplus"
  },
  {
    "text": "latest drama series Surface",
    "url": "https://tinyurl.com/surfaceappletv"
  },
  {
    "text": "\n\t\t\t\t\t\t\t\t\t\n\t\t\t\t\t\t\t\t\t\t\n\t\t\t\t\t\t\t\t\t\n\t\t\t\t\t\t\t\t",
    "url": "https://9to5mac.com/2022/07/28/how-to-watch-surface-tv-show/"
  },
  {
    "text": "Twitter raises the price of its \u2018Blue\u2019 subscription for the first time",
    "url": "https://9to5mac.com/2022/07/28/twitter-raises-blue-subscription-price/"
  },
  {
    "text": "\n\t\t\t\t\t\t\t\tFilipe Esp\u00f3sito\n\t\t\t\t\t\t\t",
    "url": "https://9to5mac.com/author/filipeesposito/"
  },
  {
    "text": "@filipeesposito",
    "url": "https://twitter.com/intent/follow?screen_name=filipeesposito&original_referer=https%3A%2F%2F9to5mac.com"
  },
  {
    "text": "Twitter",
    "url": "https://9to5mac.com/guides/twitter/"
  },
  {
    "text": "\n\t\t\t\t\t\t\t\t\n\t\t\t\t\t\t\t",
    "url": "https://9to5mac.com/2022/07/28/twitter-raises-blue-subscription-price/"
  },
  {
    "text": "6 Comments",
    "url": "https://9to5mac.com/2022/07/28/twitter-raises-blue-subscription-price/#disqus_thread"
  },
  {
    "text": "Facebook",
    "url": "https://9to5mac.com/2022/07/28/twitter-raises-blue-subscription-price/?share=facebook"
  },
  {
    "text": "Twitter",
    "url": "https://9to5mac.com/2022/07/28/twitter-raises-blue-subscription-price/?share=twitter"
  },
  {
    "text": "Pinterest",
    "url": "https://9to5mac.com/2022/07/28/twitter-raises-blue-subscription-price/?share=pinterest"
  },
  {
    "text": "LinkedIn",
    "url": "https://9to5mac.com/2022/07/28/twitter-raises-blue-subscription-price/?share=linkedin"
  },
  {
    "text": "Reddit",
    "url": "https://9to5mac.com/2022/07/28/twitter-raises-blue-subscription-price/?share=reddit"
  },
  {
    "text": "\u201cTwitter Blue,\u201d",
    "url": "https://9to5mac.com/2021/06/03/twitter-blue-subscription-service/"
  },
  {
    "text": "expand full story ",
    "url": "https://9to5mac.com/2022/07/28/twitter-raises-blue-subscription-price/#more-823979"
  },
  {
    "text": "iPhone 14 Pro always-on screen behavior previewed in new iOS 16 wallpaper details",
    "url": "https://9to5mac.com/2022/07/28/iphone-14-pro-always-on-ios-16-wallpaper/"
  },
  {
    "text": "\n\t\t\t\t\t\t\t\tFilipe Esp\u00f3sito\n\t\t\t\t\t\t\t",
    "url": "https://9to5mac.com/author/filipeesposito/"
  },
  {
    "text": "@filipeesposito",
    "url": "https://twitter.com/intent/follow?screen_name=filipeesposito&original_referer=https%3A%2F%2F9to5mac.com"
  },
  {
    "text": "iPhone 14",
    "url": "https://9to5mac.com/guides/iphone-14/"
  },
  {
    "text": "\n\t\t\t\t\t\t\t\t\n\t\t\t\t\t\t\t",
    "url": "https://9to5mac.com/2022/07/28/iphone-14-pro-always-on-ios-16-wallpaper/"
  },
  {
    "text": "31 Comments",
    "url": "https://9to5mac.com/2022/07/28/iphone-14-pro-always-on-ios-16-wallpaper/#disqus_thread"
  },
  {
    "text": "Facebook",
    "url": "https://9to5mac.com/2022/07/28/iphone-14-pro-always-on-ios-16-wallpaper/?share=facebook"
  },
  {
    "text": "Twitter",
    "url": "https://9to5mac.com/2022/07/28/iphone-14-pro-always-on-ios-16-wallpaper/?share=twitter"
  },
  {
    "text": "Pinterest",
    "url": "https://9to5mac.com/2022/07/28/iphone-14-pro-always-on-ios-16-wallpaper/?share=pinterest"
  },
  {
    "text": "LinkedIn",
    "url": "https://9to5mac.com/2022/07/28/iphone-14-pro-always-on-ios-16-wallpaper/?share=linkedin"
  },
  {
    "text": "Reddit",
    "url": "https://9to5mac.com/2022/07/28/iphone-14-pro-always-on-ios-16-wallpaper/?share=reddit"
  },
  {
    "text": "expand full story ",
    "url": "https://9to5mac.com/2022/07/28/iphone-14-pro-always-on-ios-16-wallpaper/#more-823903"
  },
  {
    "text": "Space Explored\u00a0",
    "url": "https://spaceexplored.com"
  },
  {
    "text": "",
    "url": "https://www.facebook.com/spaceexplored/"
  },
  {
    "text": "",
    "url": "https://twitter.com/space_explored"
  },
  {
    "text": "\n\t\t\t\t\t\t\t\t\n\t\t\t\t\t\t\t\tSpaceX makes renewed effort to protect the night sky\n\t\t\t\t\t\t\t",
    "url": "https://spaceexplored.com/2022/07/29/spacex-makes-renewed-effort-to-protect-the-night-sky/"
  },
  {
    "text": "\n\t\t\t\t\t\t\t\t\n\t\t\t\t\t\t\t\tSpace junk, believed to be from Crew-1\u2019s trunk, crash lands in Australia sheep farm\n\t\t\t\t\t\t\t",
    "url": "https://spaceexplored.com/2022/07/29/space-junk-crash-lands-in-australia-sheep-farm/"
  },
  {
    "text": "\n\t\t\t\t\t\t\t\t\n\t\t\t\t\t\t\t\tStarliner\u2019s spaceship growing pains have cost Boeing nearly $700 million more than planned\n\t\t\t\t\t\t\t",
    "url": "https://spaceexplored.com/2022/07/28/boeing-starliner-cost-overrun/"
  },
  {
    "text": "\n\t\t\t\t\t\t\t\t\n\t\t\t\t\t\t\t\tHan Solo\u2019s blaster from the original \u2018Star Wars\u2019 film could soon be yours\n\t\t\t\t\t\t\t",
    "url": "https://spaceexplored.com/2022/07/28/han-solo-blaster/"
  },
  {
    "text": "\n\t\t\t\t\t\t\t\t\n\t\t\t\t\t\t\t\tNASA\u2019s Mars Sample Return mission adds two helicopters after Ingenuity flights\n\t\t\t\t\t\t\t",
    "url": "https://spaceexplored.com/2022/07/27/mars-sample-return-helicopters/"
  },
  {
    "text": "",
    "url": "https://wpvip.com/?utm_source=vip_powered_wpcom&utm_medium=web&utm_campaign=VIP%20Footer%20Credit&utm_term=9to5mac.com"
  }
]
