[
  {
    "text": " ",
    "url": "/"
  },
  {
    "text": "Live",
    "url": "/live"
  },
  {
    "text": "News",
    "url": "/news"
  },
  {
    "text": "Weather",
    "url": "/weather"
  },
  {
    "text": "Good Day",
    "url": "/shows/good-day"
  },
  {
    "text": "Sports",
    "url": "/sports"
  },
  {
    "text": "Contests",
    "url": "/contests"
  },
  {
    "text": "More",
    "url": "#"
  },
  {
    "text": "Watch Live",
    "url": "/live"
  },
  {
    "text": "Expand / Collapse search",
    "url": "#"
  },
  {
    "text": "\u2630",
    "url": "#"
  },
  {
    "text": "News",
    "url": "/news"
  },
  {
    "text": "Philadelphia",
    "url": "/tag/us/pa/philadelphia"
  },
  {
    "text": "Pennsylvania",
    "url": "/tag/us/pa"
  },
  {
    "text": "New Jersey",
    "url": "/tag/us/nj"
  },
  {
    "text": "Delaware",
    "url": "/tag/us/de"
  },
  {
    "text": "More Local News",
    "url": "/local-news"
  },
  {
    "text": "National News",
    "url": "/national-news"
  },
  {
    "text": "World News",
    "url": "/tag/world"
  },
  {
    "text": "Weather",
    "url": "/weather"
  },
  {
    "text": "7-Day Forecast",
    "url": "/7-day-forecast"
  },
  {
    "text": "Closings",
    "url": "/closings"
  },
  {
    "text": "FOX Weather Blog",
    "url": "/tag/weather/fox-weather-blog"
  },
  {
    "text": "Radar",
    "url": "/interactive-radar"
  },
  {
    "text": "Temperatures",
    "url": "/current-temperatures"
  },
  {
    "text": "Watches/Warnings",
    "url": "/watches-warnings"
  },
  {
    "text": "Weather App",
    "url": "/apps"
  },
  {
    "text": "Good Day",
    "url": "/shows/good-day"
  },
  {
    "text": "'Digest' Newsletter",
    "url": "/email"
  },
  {
    "text": "Kelly's Classroom",
    "url": "/tag/series/kellys-classroom"
  },
  {
    "text": "Traffic",
    "url": "/traffic"
  },
  {
    "text": "Watch Live",
    "url": "/live"
  },
  {
    "text": "Weekend",
    "url": "/shows/good-day-weekend"
  },
  {
    "text": "Ya Gotta Try This",
    "url": "/tag/series/ya-gotta-try-this"
  },
  {
    "text": "Seen On TV",
    "url": "/tag/seen-on-tv"
  },
  {
    "text": "Sports",
    "url": "/sports"
  },
  {
    "text": "Eagles",
    "url": "/tag/nfl/philadelphia-eagles"
  },
  {
    "text": "Flyers",
    "url": "/tag/nhl/philadelphia-flyers"
  },
  {
    "text": "Phillies",
    "url": "/tag/mlb/philadelphia-phillies"
  },
  {
    "text": "76ers",
    "url": "/tag/nba/philadelphia-76ers"
  },
  {
    "text": "Union",
    "url": "/tag/mls/philadelphia-union"
  },
  {
    "text": "FOX Sports App",
    "url": "https://www.foxsports.com/mobile"
  },
  {
    "text": "Entertainment",
    "url": "/tag/entertainment"
  },
  {
    "text": "Contests",
    "url": "/contests"
  },
  {
    "text": "FOX Shows",
    "url": "/shows/fox-content"
  },
  {
    "text": "The ClassH-Room",
    "url": "/theclasshroom"
  },
  {
    "text": "The Feed AT Night",
    "url": "/shows/the-feed-at-night"
  },
  {
    "text": "Things To Do",
    "url": "/tag/lifestyle/things-to-do-philadelphia"
  },
  {
    "text": "TMZ",
    "url": "/tmz"
  },
  {
    "text": "Watch FOX Shows",
    "url": "https://www.fox.com/shows"
  },
  {
    "text": "Watch Live",
    "url": "/live"
  },
  {
    "text": "Newscasts & Replays",
    "url": "/live"
  },
  {
    "text": "LiveNOW from FOX",
    "url": "/live/newsnow/"
  },
  {
    "text": "Webcams",
    "url": "/live-cameras"
  },
  {
    "text": "Facebook Videos",
    "url": "https://www.facebook.com/pg/fox29philadelphia/videos/"
  },
  {
    "text": "FOX Soul",
    "url": "/live/soul-live/"
  },
  {
    "text": "YouTube",
    "url": "https://www.youtube.com/fox29philly"
  },
  {
    "text": "Money",
    "url": "/money"
  },
  {
    "text": "Business",
    "url": "/tag/business"
  },
  {
    "text": "Cashing In",
    "url": "/tag/series/cashing-in"
  },
  {
    "text": "Consumer",
    "url": "/tag/consumer"
  },
  {
    "text": "Deals",
    "url": "/tag/consumer/deals"
  },
  {
    "text": "Personal Finance",
    "url": "/tag/business/personal-finance"
  },
  {
    "text": "Technology",
    "url": "/tag/technology"
  },
  {
    "text": "Health",
    "url": "/tag/health"
  },
  {
    "text": "Coronavirus",
    "url": "/tag/health/coronavirus"
  },
  {
    "text": "Coronavirus Map",
    "url": "/philadelphia-coronavirus-map"
  },
  {
    "text": "Coronavirus Vaccine",
    "url": "/vaccine"
  },
  {
    "text": "Dr. Mike",
    "url": "/tag/series/doctor-mike"
  },
  {
    "text": "Dr. Oz",
    "url": "/tag/series/doctor-oz"
  },
  {
    "text": "Health Care",
    "url": "https://www.fox29.com/tag/health-care"
  },
  {
    "text": "Opioid Epidemic",
    "url": "https://www.fox29.com/tag/opioid-epidemic"
  },
  {
    "text": "Politics",
    "url": "/tag/politics"
  },
  {
    "text": "Inauguration Day",
    "url": "/tag/inauguration-day"
  },
  {
    "text": "Joe Biden",
    "url": "/tag/people/joe-biden"
  },
  {
    "text": "Kamala Harris",
    "url": "https://www.fox29.com/tag/people/kamala-harris"
  },
  {
    "text": "2022 Elections",
    "url": "/tag/2022-midterm-elections"
  },
  {
    "text": "Donald J. Trump",
    "url": "/tag/people/donald-j-trump"
  },
  {
    "text": "Philly City Council",
    "url": "https://www.fox29.com/tag/politics/philadelphia-city-council"
  },
  {
    "text": "FOX 29 Originals",
    "url": "/tag/series"
  },
  {
    "text": "News Specials",
    "url": "/tag/series/fox-29-news-specials"
  },
  {
    "text": "Hank's Take",
    "url": "/tag/series/hanks-take"
  },
  {
    "text": "In Focus",
    "url": "/tag/series/in-focus"
  },
  {
    "text": "Kelly Drives",
    "url": "/tag/kelly-drives"
  },
  {
    "text": "Our Race Reality",
    "url": "/tag/series/our-race-reality"
  },
  {
    "text": "Save Our Streets",
    "url": "/shows/save-our-streets"
  },
  {
    "text": "The 215 ",
    "url": "/shows/the-215"
  },
  {
    "text": "The Pulse",
    "url": "/tag/the-pulse"
  },
  {
    "text": "Regional News",
    "url": "/tag/us/pa"
  },
  {
    "text": "New Jersey News - My9NJ",
    "url": "https://www.my9nj.com/"
  },
  {
    "text": "New York News - FOX 5 NY",
    "url": "https://www.fox5ny.com/"
  },
  {
    "text": "Washington DC News - FOX 5 DC",
    "url": "https://www.fox5dc.com/"
  },
  {
    "text": "About Us",
    "url": "/about-us"
  },
  {
    "text": "Apps",
    "url": "/apps"
  },
  {
    "text": "Contact Us",
    "url": "/contact-us"
  },
  {
    "text": "FCC Public File",
    "url": "/public-file-inquiries"
  },
  {
    "text": "FCC Applications",
    "url": "https://www.fox29.com/fcc-applications"
  },
  {
    "text": "How To Advertise",
    "url": "/advertise"
  },
  {
    "text": "Personalities",
    "url": "/person/all"
  },
  {
    "text": "TV Listings",
    "url": "/whatsonfox"
  },
  {
    "text": "Work For Us",
    "url": "/work-for-us"
  },
  {
    "text": "  ",
    "url": "/news/mega-millions-winning-numbers-friday-1-billion-drawing"
  },
  {
    "text": "Mega Millions winning numbers: $1.28B Friday drawing",
    "url": "/news/mega-millions-winning-numbers-friday-1-billion-drawing"
  },
  {
    "text": "  ",
    "url": "/news/firefighters-respond-to-jims-steaks-on-south-street"
  },
  {
    "text": "Jim's Steaks fire: Firefighters get multi-alarm fire under control after four hours",
    "url": "/news/firefighters-respond-to-jims-steaks-on-south-street"
  },
  {
    "text": "  ",
    "url": "/news/weather-authority-overnight-showers-leads-to-near-perfect-weekend-across-the-region"
  },
  {
    "text": "Weather Authority: Overnight showers leads to near-perfect weekend across the region",
    "url": "/news/weather-authority-overnight-showers-leads-to-near-perfect-weekend-across-the-region"
  },
  {
    "text": "  ",
    "url": "/news/video-2-suspects-sought-for-firing-into-crowd-of-people-shooting-child-in-east-germantown"
  },
  {
    "text": "Video: 2 suspects sought for firing into crowd of people, shooting child in East Germantown",
    "url": "/news/video-2-suspects-sought-for-firing-into-crowd-of-people-shooting-child-in-east-germantown"
  },
  {
    "text": "  ",
    "url": "/news/fanta-bility-shooting-findings-of-report-on-police-killing-of-8-year-old-withheld-1"
  },
  {
    "text": "Fanta Bility shooting: Findings of report on police killing of 8-year-old withheld",
    "url": "/news/fanta-bility-shooting-findings-of-report-on-police-killing-of-8-year-old-withheld-1"
  },
  {
    "text": "  ",
    "url": "/news/lucky-to-be-alive-arthur-corgi-survives-shot-head-pspca"
  },
  {
    "text": "'Lucky to be alive': Arthur the corgi survives after being shot in the head, Pennsylvania SPCA says",
    "url": "/news/lucky-to-be-alive-arthur-corgi-survives-shot-head-pspca"
  },
  {
    "text": "  ",
    "url": "/news/philadelphia-street-renamed-after-oldest-living-american-olympic-medalist"
  },
  {
    "text": "Philadelphia street renamed after oldest living American Olympic medalist",
    "url": "/news/philadelphia-street-renamed-after-oldest-living-american-olympic-medalist"
  },
  {
    "text": "  ",
    "url": "/news/police-man-critical-after-being-shot-in-the-head-in-kensington"
  },
  {
    "text": "Police: Man critical after being shot in the head in Kensington",
    "url": "/news/police-man-critical-after-being-shot-in-the-head-in-kensington"
  },
  {
    "text": "  ",
    "url": "/news/wolf-sues-to-stop-gop-backed-amendments-on-abortion-voting-1"
  },
  {
    "text": "Wolf sues to stop GOP-backed amendments on abortion, voting",
    "url": "/news/wolf-sues-to-stop-gop-backed-amendments-on-abortion-voting-1"
  },
  {
    "text": "  ",
    "url": "/news/police-26-year-old-dead-after-south-philly-shooting-wednesday-night"
  },
  {
    "text": "Police: Member of local music group Brotherly Love fatally shot in front of his South Philadelphia home",
    "url": "/news/police-26-year-old-dead-after-south-philly-shooting-wednesday-night"
  },
  {
    "text": "  ",
    "url": "/news/police-woman-arrested-for-posing-as-new-jersey-child-protective-services-worker"
  },
  {
    "text": "Police: Woman arrested for posing as New Jersey child protective services worker",
    "url": "/news/police-woman-arrested-for-posing-as-new-jersey-child-protective-services-worker"
  },
  {
    "text": "  ",
    "url": "/news/will-smith-apologizes-chris-rock-oscars-slap-new-video-july-2022-my-behavior-was-unacceptable"
  },
  {
    "text": "Will Smith apologizes to Chris Rock for Oscars slap in new video: 'My behavior was unacceptable'",
    "url": "/news/will-smith-apologizes-chris-rock-oscars-slap-new-video-july-2022-my-behavior-was-unacceptable"
  },
  {
    "text": "  ",
    "url": "/news/kentucky-flooding-appalachia-death-toll-updates"
  },
  {
    "text": "Kentucky floods kill at least 16 as governor warns toll will be 'a lot higher'",
    "url": "/news/kentucky-flooding-appalachia-death-toll-updates"
  },
  {
    "text": "Philadelphia",
    "url": "https://www.fox29.com/weather"
  },
  {
    "text": "  video",
    "url": "/video/1099180"
  },
  {
    "text": "Fanta Bility shooting: Findings of report on police killing of 8-year-old withheld",
    "url": "/video/1099180"
  },
  {
    "text": "  video",
    "url": "/video/1099178"
  },
  {
    "text": "Jim's Steaks fire: Firefighters get multi-alarm fire under control after four hours",
    "url": "/video/1099178"
  },
  {
    "text": "  video",
    "url": "/video/1099177"
  },
  {
    "text": "Mega Millions jackpot swells to $1.28B",
    "url": "/video/1099177"
  },
  {
    "text": "  video",
    "url": "/video/1099163"
  },
  {
    "text": "Weather Authority: Friday, 10 p.m. update",
    "url": "/video/1099163"
  },
  {
    "text": "  video",
    "url": "/video/1099059"
  },
  {
    "text": "Fanta Bility shooting: Findings of report on police killing of 8-year-old withheld",
    "url": "/video/1099059"
  },
  {
    "text": "  video",
    "url": "/video/1099009"
  },
  {
    "text": "Weather Authority: Friday, 5 p.m. update",
    "url": "/video/1099009"
  },
  {
    "text": "\n          Subscribe to FOX 29 on YouTube\n        ",
    "url": "https://www.youtube.com/fox29philly?sub_confirmation=1"
  },
  {
    "text": " ",
    "url": "https://www.youtube.com/fox29philly?sub_confirmation=1"
  },
  {
    "text": "\n          Exclusive FOX content\n        ",
    "url": "/shows/fox-content"
  },
  {
    "text": " ",
    "url": "/shows/fox-content"
  },
  {
    "text": "  video",
    "url": "/video/1096497"
  },
  {
    "text": "Save Our Streets: Is it the guns?",
    "url": "/video/1096497"
  },
  {
    "text": "  video",
    "url": "/video/1093752"
  },
  {
    "text": "Best of Preston & Steve on Good Day Philadelphia",
    "url": "/video/1093752"
  },
  {
    "text": "  video",
    "url": "/video/1090954"
  },
  {
    "text": "Extreme Weather: Summer storms cause severe damage",
    "url": "/video/1090954"
  },
  {
    "text": "Local News",
    "url": "/local-news"
  },
  {
    "text": "View More",
    "url": "/local-news"
  },
  {
    "text": "  ",
    "url": "/news/fanta-bility-shooting-findings-of-report-on-police-killing-of-8-year-old-withheld-1"
  },
  {
    "text": "Fanta Bility shooting: Findings of report on police killing of 8-year-old withheld",
    "url": "/news/fanta-bility-shooting-findings-of-report-on-police-killing-of-8-year-old-withheld-1"
  },
  {
    "text": "  ",
    "url": "/news/firefighters-respond-to-jims-steaks-on-south-street"
  },
  {
    "text": "Jim's Steaks fire: Firefighters get multi-alarm fire under control after four hours",
    "url": "/news/firefighters-respond-to-jims-steaks-on-south-street"
  },
  {
    "text": "  ",
    "url": "/news/police-man-critical-after-being-shot-in-the-head-in-kensington"
  },
  {
    "text": "Police: Man critical after being shot in the head in Kensington",
    "url": "/news/police-man-critical-after-being-shot-in-the-head-in-kensington"
  },
  {
    "text": "  ",
    "url": "/news/germantown-community-calls-for-peace-amid-violent-summer-of-gun-violence"
  },
  {
    "text": "Germantown community calls for peace amid violent summer of gun violence",
    "url": "/news/germantown-community-calls-for-peace-amid-violent-summer-of-gun-violence"
  },
  {
    "text": "  ",
    "url": "/news/pennsylvania-teacher-suspended-after-jan-6-fired-for-not-working"
  },
  {
    "text": "Pennsylvania teacher suspended after Jan. 6 fired for not working",
    "url": "/news/pennsylvania-teacher-suspended-after-jan-6-fired-for-not-working"
  },
  {
    "text": "  ",
    "url": "/news/video-2-suspects-sought-for-firing-into-crowd-of-people-shooting-child-in-east-germantown"
  },
  {
    "text": "Video: 2 suspects sought for firing into crowd of people, shooting child in East Germantown",
    "url": "/news/video-2-suspects-sought-for-firing-into-crowd-of-people-shooting-child-in-east-germantown"
  },
  {
    "text": "Good Day Philadelphia",
    "url": "/shows/good-day"
  },
  {
    "text": "View More",
    "url": "/shows/good-day"
  },
  {
    "text": "  video",
    "url": "/video/1098852"
  },
  {
    "text": "Annual East Passyunk Car Show & Street Festival returns this weekend",
    "url": "/video/1098852"
  },
  {
    "text": "  video",
    "url": "/video/1098849"
  },
  {
    "text": "Whatcha Makin?: July 29, 2022",
    "url": "/video/1098849"
  },
  {
    "text": "  video",
    "url": "/video/1098848"
  },
  {
    "text": "Treetrails Adventures opens in Bucks County",
    "url": "/video/1098848"
  },
  {
    "text": "  video",
    "url": "/video/1098845"
  },
  {
    "text": "National Chicken Wing Day: Chef Chad Rosenthal whips up smoked wings",
    "url": "/video/1098845"
  },
  {
    "text": "  video",
    "url": "/video/1098842"
  },
  {
    "text": "National Chicken Wing Day: Korean Fried Chicken at Southgate",
    "url": "/video/1098842"
  },
  {
    "text": "  video",
    "url": "/video/1098838"
  },
  {
    "text": "Hot Wheels Monster Truck Show heading to the Wells Fargo Center",
    "url": "/video/1098838"
  },
  {
    "text": "Coronavirus",
    "url": "/tag/health/coronavirus"
  },
  {
    "text": "View More",
    "url": "/tag/health/coronavirus"
  },
  {
    "text": "  ",
    "url": "/news/moderna-covid-omicron-vaccine-pfizer-winter-booster-shots"
  },
  {
    "text": "COVID omicron vaccine: US reaches deal with Moderna for winter booster shots",
    "url": "/news/moderna-covid-omicron-vaccine-pfizer-winter-booster-shots"
  },
  {
    "text": "  ",
    "url": "/news/biden-feeling-much-much-better-after-getting-ba-5-covid-variant"
  },
  {
    "text": "Biden improves 'significantly' after getting BA.5 COVID variant",
    "url": "/news/biden-feeling-much-much-better-after-getting-ba-5-covid-variant"
  },
  {
    "text": "  ",
    "url": "/news/biden-covid-19-ba5-strain"
  },
  {
    "text": "Biden likely has highly contagious BA.5 strain of COVID-19, doctor says",
    "url": "/news/biden-covid-19-ba5-strain"
  },
  {
    "text": "  ",
    "url": "/news/biden-tests-positive-for-covid-19-white-house-mild-symptoms"
  },
  {
    "text": "Biden tests positive for COVID-19, has \u2018very mild\u2019 symptoms, WH says",
    "url": "/news/biden-tests-positive-for-covid-19-white-house-mild-symptoms"
  },
  {
    "text": "  ",
    "url": "/news/a-beacon-of-hope-n-j-officer-tours-landmark-that-gave-him-inspiration-during-covid-battle"
  },
  {
    "text": "'A beacon of hope': N.J. officer tours landmark that gave him inspiration during COVID battle",
    "url": "/news/a-beacon-of-hope-n-j-officer-tours-landmark-that-gave-him-inspiration-during-covid-battle"
  },
  {
    "text": "  video",
    "url": "/video/1093836"
  },
  {
    "text": "N.J. officer tours landmark that gave him inspiration during COVID battle",
    "url": "/video/1093836"
  },
  {
    "text": "Save Our Streets",
    "url": "/shows/save-our-streets"
  },
  {
    "text": "View More",
    "url": "/shows/save-our-streets"
  },
  {
    "text": "  ",
    "url": "/news/germantown-community-calls-for-peace-amid-violent-summer-of-gun-violence"
  },
  {
    "text": "Germantown community calls for peace amid violent summer of gun violence",
    "url": "/news/germantown-community-calls-for-peace-amid-violent-summer-of-gun-violence"
  },
  {
    "text": "  video",
    "url": "/video/1096497"
  },
  {
    "text": "Save Our Streets: Is it the guns?",
    "url": "/video/1096497"
  },
  {
    "text": "  ",
    "url": "/news/workshop-teaches-philadelphia-teens-to-protect-themselves-while-building-trust-with-police"
  },
  {
    "text": "Workshop teaches Philadelphia teens to protect themselves, while building trust with police",
    "url": "/news/workshop-teaches-philadelphia-teens-to-protect-themselves-while-building-trust-with-police"
  },
  {
    "text": "  video",
    "url": "/video/1096260"
  },
  {
    "text": "Workshop teaches Philadelphia teens to protect themselves, while building trust with police",
    "url": "/video/1096260"
  },
  {
    "text": "  video",
    "url": "/video/1095572"
  },
  {
    "text": "'Shot: We The Mothers' exhibit highlights mothers who lost children to gun violence",
    "url": "/video/1095572"
  },
  {
    "text": "  video",
    "url": "/video/1093288"
  },
  {
    "text": "Pool pop ups dedicated to teaching Philadelphia teens how to swim, become lifeguards",
    "url": "/video/1093288"
  },
  {
    "text": "Politics",
    "url": "/tag/politics"
  },
  {
    "text": "View More",
    "url": "/tag/politics"
  },
  {
    "text": "  ",
    "url": "/news/wolf-sues-to-stop-gop-backed-amendments-on-abortion-voting-1"
  },
  {
    "text": "Wolf sues to stop GOP-backed amendments on abortion, voting",
    "url": "/news/wolf-sues-to-stop-gop-backed-amendments-on-abortion-voting-1"
  },
  {
    "text": "  ",
    "url": "/news/biden-xi-hold-fifth-talk"
  },
  {
    "text": "Biden, Xi make plans to meet, official says; China's leader has strong words on Taiwan",
    "url": "/news/biden-xi-hold-fifth-talk"
  },
  {
    "text": "  ",
    "url": "/news/ev-tax-credit-senate-deal-climate-inflation-bill-electric-vehicles"
  },
  {
    "text": "Senate deal on climate, inflation bill would make it easier to buy electric vehicles",
    "url": "/news/ev-tax-credit-senate-deal-climate-inflation-bill-electric-vehicles"
  },
  {
    "text": "  ",
    "url": "/news/fox-news-poll-oz-supporters-lack-enthusiasm-in-pennsylvania-senate-race"
  },
  {
    "text": "Fox News Poll: Oz supporters lack enthusiasm in Pennsylvania Senate race",
    "url": "/news/fox-news-poll-oz-supporters-lack-enthusiasm-in-pennsylvania-senate-race"
  },
  {
    "text": "  ",
    "url": "/news/climate-health-care-inflation-bill-manchin-schumer-democrats-package-explained"
  },
  {
    "text": "What's in, and out, of Democrats' climate, health care and inflation bill",
    "url": "/news/climate-health-care-inflation-bill-manchin-schumer-democrats-package-explained"
  },
  {
    "text": "  ",
    "url": "/news/four-pennsylvania-universities-reject-gop-call-to-freeze-tuition"
  },
  {
    "text": "Four Pennsylvania universities reject GOP call to freeze tuition",
    "url": "/news/four-pennsylvania-universities-reject-gop-call-to-freeze-tuition"
  },
  {
    "text": "Sports",
    "url": "/sports"
  },
  {
    "text": "View More",
    "url": "/sports"
  },
  {
    "text": "  ",
    "url": "/sports/nil-deals-college-football-player-70-endorsements"
  },
  {
    "text": "NIL deals: College football, track star known as \u2018King of NIL\u2019 has 70 endorsements",
    "url": "/sports/nil-deals-college-football-player-70-endorsements"
  },
  {
    "text": "  ",
    "url": "/news/philadelphia-street-renamed-after-oldest-living-american-olympic-medalist"
  },
  {
    "text": "Philadelphia street renamed after oldest living American Olympic medalist",
    "url": "/news/philadelphia-street-renamed-after-oldest-living-american-olympic-medalist"
  },
  {
    "text": "  ",
    "url": "/news/schwarber-wheeler-power-phillies-to-8-7-win-over-pirates-1"
  },
  {
    "text": "Schwarber, Wheeler power Phillies to 8-7 win over Pirates",
    "url": "/news/schwarber-wheeler-power-phillies-to-8-7-win-over-pirates-1"
  },
  {
    "text": "  ",
    "url": "/news/harden-76ers-make-it-official-on-2-year-68-million-deal-1"
  },
  {
    "text": "Harden, 76ers make it official on 2-year, $68 million deal",
    "url": "/news/harden-76ers-make-it-official-on-2-year-68-million-deal-1"
  },
  {
    "text": "  ",
    "url": "/news/us-basketball-star-brittney-griner-testifies-at-russia-drug-trial"
  },
  {
    "text": "US basketball star Brittney Griner testifies that poor translation led to her arrest in Russia",
    "url": "/news/us-basketball-star-brittney-griner-testifies-at-russia-drug-trial"
  },
  {
    "text": "  ",
    "url": "/news/former-temple-coach-james-skip-wilson-who-led-baseball-team-to-1034-wins-dies-at-92"
  },
  {
    "text": "Former Temple coach James \u201cSkip\u201d Wilson, who led baseball team to 1,034 wins, dies at 92",
    "url": "/news/former-temple-coach-james-skip-wilson-who-led-baseball-team-to-1034-wins-dies-at-92"
  },
  {
    "text": "U.S. & World News",
    "url": "/national-news"
  },
  {
    "text": "View More",
    "url": "/national-news"
  },
  {
    "text": "  ",
    "url": "/news/here-are-fridays-numbers-for-the-1-28-billion-mega-millions-lottery-jackpot"
  },
  {
    "text": "$1.28 billion Mega Millions jackpot: Here are the winning numbers for Friday\u2019s drawing",
    "url": "/news/here-are-fridays-numbers-for-the-1-28-billion-mega-millions-lottery-jackpot"
  },
  {
    "text": "  ",
    "url": "/news/woman-who-allegedly-shot-husband-in-dc-hotel-over-child-molestation-claims-to-remain-behind-bars"
  },
  {
    "text": "Woman who allegedly shot husband in DC hotel over child molestation claims to remain behind bars",
    "url": "/news/woman-who-allegedly-shot-husband-in-dc-hotel-over-child-molestation-claims-to-remain-behind-bars"
  },
  {
    "text": "  ",
    "url": "/news/house-passes-semi-automatic-gun-ban-after-18-year-lapse"
  },
  {
    "text": "House passes semi-automatic gun ban after 18-year lapse",
    "url": "/news/house-passes-semi-automatic-gun-ban-after-18-year-lapse"
  },
  {
    "text": "  ",
    "url": "/news/las-vegas-strip-multiple-casinos-flooded-overnight-by-monsoon-storm"
  },
  {
    "text": "Las Vegas Strip, multiple casinos flooded overnight by monsoon storm",
    "url": "/news/las-vegas-strip-multiple-casinos-flooded-overnight-by-monsoon-storm"
  },
  {
    "text": "  ",
    "url": "/news/hyundai-subsidiary-allegedly-uses-child-labor-report"
  },
  {
    "text": "Hyundai subsidiary accused of using child labor at Alabama factory: report",
    "url": "/news/hyundai-subsidiary-allegedly-uses-child-labor-report"
  },
  {
    "text": "  ",
    "url": "/news/lucky-to-be-alive-arthur-corgi-survives-shot-head-pspca"
  },
  {
    "text": "'Lucky to be alive': Arthur the corgi survives after being shot in the head, Pennsylvania SPCA says",
    "url": "/news/lucky-to-be-alive-arthur-corgi-survives-shot-head-pspca"
  },
  {
    "text": "Money",
    "url": "/money"
  },
  {
    "text": "View More",
    "url": "/money"
  },
  {
    "text": "  ",
    "url": "/news/mega-millions-winning-numbers-friday-1-billion-drawing"
  },
  {
    "text": "Mega Millions winning numbers: $1.28B Friday drawing",
    "url": "/news/mega-millions-winning-numbers-friday-1-billion-drawing"
  },
  {
    "text": "  ",
    "url": "/news/tiktok-pink-sauce-why-is-everyone-freaking-out-about-this-controversial-condiment"
  },
  {
    "text": "TikTok pink sauce: Why is everyone freaking out about this controversial condiment?",
    "url": "/news/tiktok-pink-sauce-why-is-everyone-freaking-out-about-this-controversial-condiment"
  },
  {
    "text": "  ",
    "url": "/news/elder-index-shows-millions-of-american-seniors-cant-afford-basic-living-costs"
  },
  {
    "text": "Elder Index shows millions of American seniors can\u2019t afford basic living costs",
    "url": "/news/elder-index-shows-millions-of-american-seniors-cant-afford-basic-living-costs"
  },
  {
    "text": "  ",
    "url": "/news/10-times-hitting-the-lottery-jackpot-ended-in-disaster-i-wish-id-torn-that-ticket-up"
  },
  {
    "text": "10 times hitting the lottery jackpot ended in disaster: 'I wish I'd torn that ticket up'",
    "url": "/news/10-times-hitting-the-lottery-jackpot-ended-in-disaster-i-wish-id-torn-that-ticket-up"
  },
  {
    "text": "  ",
    "url": "/news/how-to-recession-proof-your-life"
  },
  {
    "text": "How to recession-proof your life",
    "url": "/news/how-to-recession-proof-your-life"
  },
  {
    "text": "  ",
    "url": "/news/ev-tax-credit-senate-deal-climate-inflation-bill-electric-vehicles"
  },
  {
    "text": "Senate deal on climate, inflation bill would make it easier to buy electric vehicles",
    "url": "/news/ev-tax-credit-senate-deal-climate-inflation-bill-electric-vehicles"
  },
  {
    "text": "Entertainment",
    "url": "/tag/entertainment"
  },
  {
    "text": "View More",
    "url": "/tag/entertainment"
  },
  {
    "text": "  ",
    "url": "/news/shark-month-bitefest-returns-to-tubi-with-two-shark-tastic-original-films"
  },
  {
    "text": "Shark Month: Bitefest returns to Tubi with two shark-tastic original films",
    "url": "/news/shark-month-bitefest-returns-to-tubi-with-two-shark-tastic-original-films"
  },
  {
    "text": "  ",
    "url": "/news/bob-dylan-sexual-abuse-accuser-drops-lawsuit-after-allegedly-erasing-evidence-reports"
  },
  {
    "text": "Bob Dylan sexual abuse accuser drops lawsuit after allegedly erasing evidence: reports",
    "url": "/news/bob-dylan-sexual-abuse-accuser-drops-lawsuit-after-allegedly-erasing-evidence-reports"
  },
  {
    "text": "  ",
    "url": "/news/pop-star-shakira-could-face-more-than-8-years-in-prison-for-alleged-tax-fraud"
  },
  {
    "text": "Pop star Shakira could face more than 8 years in prison for alleged tax fraud",
    "url": "/news/pop-star-shakira-could-face-more-than-8-years-in-prison-for-alleged-tax-fraud"
  },
  {
    "text": "  ",
    "url": "/news/dc-league-of-super-pets-review-the-rock-how-to-watch"
  },
  {
    "text": "Movie review: \u2018DC League of Super-Pets\u2019 has delightful Saturday morning cartoon vibes",
    "url": "/news/dc-league-of-super-pets-review-the-rock-how-to-watch"
  },
  {
    "text": "  ",
    "url": "/news/will-smith-apologizes-chris-rock-oscars-slap-new-video-july-2022-my-behavior-was-unacceptable"
  },
  {
    "text": "Will Smith apologizes to Chris Rock for Oscars slap in new video: 'My behavior was unacceptable'",
    "url": "/news/will-smith-apologizes-chris-rock-oscars-slap-new-video-july-2022-my-behavior-was-unacceptable"
  },
  {
    "text": "  ",
    "url": "/news/beyonce-renaissance-album-kelis-accusations-song-theft"
  },
  {
    "text": "Beyonc\u00e9 releases new album \u2018Renaissance\u2019 as singer Kelis accuses her of song 'theft'",
    "url": "/news/beyonce-renaissance-album-kelis-accusations-song-theft"
  },
  {
    "text": "News",
    "url": "/news"
  },
  {
    "text": "Philadelphia",
    "url": "/tag/us/pa/philadelphia"
  },
  {
    "text": "Pennsylvania",
    "url": "/tag/us/pa"
  },
  {
    "text": "New Jersey",
    "url": "/tag/us/nj"
  },
  {
    "text": "Delaware",
    "url": "/tag/us/de"
  },
  {
    "text": "More Local News",
    "url": "/local-news"
  },
  {
    "text": "National News",
    "url": "/national-news"
  },
  {
    "text": "World News",
    "url": "/tag/world"
  },
  {
    "text": "Weather",
    "url": "/weather"
  },
  {
    "text": "7-Day Forecast",
    "url": "/7-day-forecast"
  },
  {
    "text": "Closings",
    "url": "/closings"
  },
  {
    "text": "FOX Weather Blog",
    "url": "/tag/weather/fox-weather-blog"
  },
  {
    "text": "Radar",
    "url": "/interactive-radar"
  },
  {
    "text": "Temperatures",
    "url": "/current-temperatures"
  },
  {
    "text": "Watches/Warnings",
    "url": "/watches-warnings"
  },
  {
    "text": "Weather App",
    "url": "/apps"
  },
  {
    "text": "Good Day",
    "url": "/shows/good-day"
  },
  {
    "text": "'Digest' Newsletter",
    "url": "/email"
  },
  {
    "text": "Kelly's Classroom",
    "url": "/tag/series/kellys-classroom"
  },
  {
    "text": "Traffic",
    "url": "/traffic"
  },
  {
    "text": "Watch Live",
    "url": "/live"
  },
  {
    "text": "Weekend",
    "url": "/shows/good-day-weekend"
  },
  {
    "text": "Ya Gotta Try This",
    "url": "/tag/series/ya-gotta-try-this"
  },
  {
    "text": "Seen On TV",
    "url": "/tag/seen-on-tv"
  },
  {
    "text": "Sports",
    "url": "/sports"
  },
  {
    "text": "Eagles",
    "url": "/tag/nfl/philadelphia-eagles"
  },
  {
    "text": "Flyers",
    "url": "/tag/nhl/philadelphia-flyers"
  },
  {
    "text": "Phillies",
    "url": "/tag/mlb/philadelphia-phillies"
  },
  {
    "text": "76ers",
    "url": "/tag/nba/philadelphia-76ers"
  },
  {
    "text": "Union",
    "url": "/tag/mls/philadelphia-union"
  },
  {
    "text": "FOX Sports App",
    "url": "https://www.foxsports.com/mobile"
  },
  {
    "text": "Entertainment",
    "url": "/tag/entertainment"
  },
  {
    "text": "Contests",
    "url": "/contests"
  },
  {
    "text": "FOX Shows",
    "url": "/shows/fox-content"
  },
  {
    "text": "The ClassH-Room",
    "url": "/theclasshroom"
  },
  {
    "text": "The Feed AT Night",
    "url": "/shows/the-feed-at-night"
  },
  {
    "text": "Things To Do",
    "url": "/tag/lifestyle/things-to-do-philadelphia"
  },
  {
    "text": "TMZ",
    "url": "/tmz"
  },
  {
    "text": "Watch FOX Shows",
    "url": "https://www.fox.com/shows"
  },
  {
    "text": "Watch Live",
    "url": "/live"
  },
  {
    "text": "Newscasts & Replays",
    "url": "/live"
  },
  {
    "text": "LiveNOW from FOX",
    "url": "/live/newsnow/"
  },
  {
    "text": "Webcams",
    "url": "/live-cameras"
  },
  {
    "text": "Facebook Videos",
    "url": "https://www.facebook.com/pg/fox29philadelphia/videos/"
  },
  {
    "text": "FOX Soul",
    "url": "/live/soul-live/"
  },
  {
    "text": "YouTube",
    "url": "https://www.youtube.com/fox29philly"
  },
  {
    "text": "Money",
    "url": "/money"
  },
  {
    "text": "Business",
    "url": "/tag/business"
  },
  {
    "text": "Cashing In",
    "url": "/tag/series/cashing-in"
  },
  {
    "text": "Consumer",
    "url": "/tag/consumer"
  },
  {
    "text": "Deals",
    "url": "/tag/consumer/deals"
  },
  {
    "text": "Personal Finance",
    "url": "/tag/business/personal-finance"
  },
  {
    "text": "Technology",
    "url": "/tag/technology"
  },
  {
    "text": "Health",
    "url": "/tag/health"
  },
  {
    "text": "Coronavirus",
    "url": "/tag/health/coronavirus"
  },
  {
    "text": "Coronavirus Map",
    "url": "/philadelphia-coronavirus-map"
  },
  {
    "text": "Coronavirus Vaccine",
    "url": "/vaccine"
  },
  {
    "text": "Dr. Mike",
    "url": "/tag/series/doctor-mike"
  },
  {
    "text": "Dr. Oz",
    "url": "/tag/series/doctor-oz"
  },
  {
    "text": "Health Care",
    "url": "https://www.fox29.com/tag/health-care"
  },
  {
    "text": "Opioid Epidemic",
    "url": "https://www.fox29.com/tag/opioid-epidemic"
  },
  {
    "text": "Politics",
    "url": "/tag/politics"
  },
  {
    "text": "Inauguration Day",
    "url": "/tag/inauguration-day"
  },
  {
    "text": "Joe Biden",
    "url": "/tag/people/joe-biden"
  },
  {
    "text": "Kamala Harris",
    "url": "https://www.fox29.com/tag/people/kamala-harris"
  },
  {
    "text": "2022 Elections",
    "url": "/tag/2022-midterm-elections"
  },
  {
    "text": "Donald J. Trump",
    "url": "/tag/people/donald-j-trump"
  },
  {
    "text": "Philly City Council",
    "url": "https://www.fox29.com/tag/politics/philadelphia-city-council"
  },
  {
    "text": "FOX 29 Originals",
    "url": "/tag/series"
  },
  {
    "text": "News Specials",
    "url": "/tag/series/fox-29-news-specials"
  },
  {
    "text": "Hank's Take",
    "url": "/tag/series/hanks-take"
  },
  {
    "text": "In Focus",
    "url": "/tag/series/in-focus"
  },
  {
    "text": "Kelly Drives",
    "url": "/tag/kelly-drives"
  },
  {
    "text": "Our Race Reality",
    "url": "/tag/series/our-race-reality"
  },
  {
    "text": "Save Our Streets",
    "url": "/shows/save-our-streets"
  },
  {
    "text": "The 215 ",
    "url": "/shows/the-215"
  },
  {
    "text": "The Pulse",
    "url": "/tag/the-pulse"
  },
  {
    "text": "Regional News",
    "url": "/tag/us/pa"
  },
  {
    "text": "New Jersey News - My9NJ",
    "url": "https://www.my9nj.com/"
  },
  {
    "text": "New York News - FOX 5 NY",
    "url": "https://www.fox5ny.com/"
  },
  {
    "text": "Washington DC News - FOX 5 DC",
    "url": "https://www.fox5dc.com/"
  },
  {
    "text": "About Us",
    "url": "/about-us"
  },
  {
    "text": "Apps",
    "url": "/apps"
  },
  {
    "text": "Contact Us",
    "url": "/contact-us"
  },
  {
    "text": "FCC Public File",
    "url": "/public-file-inquiries"
  },
  {
    "text": "FCC Applications",
    "url": "https://www.fox29.com/fcc-applications"
  },
  {
    "text": "How To Advertise",
    "url": "/advertise"
  },
  {
    "text": "Personalities",
    "url": "/person/all"
  },
  {
    "text": "TV Listings",
    "url": "/whatsonfox"
  },
  {
    "text": "Work For Us",
    "url": "/work-for-us"
  },
  {
    "text": "facebook",
    "url": "https://www.facebook.com/fox29philadelphia"
  },
  {
    "text": "twitter",
    "url": "https://twitter.com/FOX29philly"
  },
  {
    "text": "instagram",
    "url": "https://www.instagram.com/fox29philly"
  },
  {
    "text": "youtube",
    "url": "https://www.youtube.com/fox29philly"
  },
  {
    "text": "email",
    "url": "https://www.fox29.com/email"
  },
  {
    "text": "",
    "url": "/"
  },
  {
    "text": "About Us",
    "url": "/about-us"
  },
  {
    "text": "Privacy Policy",
    "url": "/privacy-policy"
  },
  {
    "text": "Terms of Service",
    "url": "/terms-of-service"
  },
  {
    "text": "Do Not Sell my Personal Information",
    "url": "/do-not-sell-my-personal-information"
  },
  {
    "text": "FCC Public File",
    "url": "/public-file-inquiries"
  },
  {
    "text": "EEO Public File",
    "url": "https://publicfiles.fcc.gov/tv-profile/wtxf-tv/equal-employment-opportunity-records/"
  },
  {
    "text": "Closed Captioning",
    "url": "/closed-captioning"
  },
  {
    "text": "Work For Us",
    "url": "/work-for-us"
  },
  {
    "text": "Contact Us",
    "url": "/contact-us"
  }
]
